{
"meta":{"test_sets":[],"test_metrics":[],"learn_metrics":[{"best_value":"Min","name":"RMSE"}],"launch_mode":"Train","parameters":"","iteration_count":1000,"learn_sets":["learn"],"name":"experiment"},
"iterations":[
{"learn":[14.59871775],"iteration":0,"passed_time":0.05955474599,"remaining_time":59.49519125},
{"learn":[14.22518863],"iteration":1,"passed_time":0.05995147487,"remaining_time":29.91578596},
{"learn":[13.8866124],"iteration":2,"passed_time":0.06028349886,"remaining_time":20.03421612},
{"learn":[13.52356875],"iteration":3,"passed_time":0.06059789879,"remaining_time":15.0888768},
{"learn":[13.18870211],"iteration":4,"passed_time":0.06091188207,"remaining_time":12.12146453},
{"learn":[12.9124226],"iteration":5,"passed_time":0.06124594762,"remaining_time":10.14641199},
{"learn":[12.60003351],"iteration":6,"passed_time":0.06158692947,"remaining_time":8.736545852},
{"learn":[12.32990573],"iteration":7,"passed_time":0.06191624527,"remaining_time":7.677614413},
{"learn":[12.0660619],"iteration":8,"passed_time":0.0623000165,"remaining_time":6.859924039},
{"learn":[11.77309809],"iteration":9,"passed_time":0.06260750013,"remaining_time":6.198142513},
{"learn":[11.49227636],"iteration":10,"passed_time":0.06294952359,"remaining_time":5.659734439},
{"learn":[11.26264833],"iteration":11,"passed_time":0.06328208922,"remaining_time":5.210225346},
{"learn":[11.04260393],"iteration":12,"passed_time":0.06361852964,"remaining_time":4.83011452},
{"learn":[10.79916926],"iteration":13,"passed_time":0.06391638878,"remaining_time":4.501539953},
{"learn":[10.5541002],"iteration":14,"passed_time":0.0642259973,"remaining_time":4.217507156},
{"learn":[10.31918115],"iteration":15,"passed_time":0.06456731246,"remaining_time":3.970889716},
{"learn":[10.10004441],"iteration":16,"passed_time":0.06490854429,"remaining_time":3.75324112},
{"learn":[9.894556723],"iteration":17,"passed_time":0.06519932048,"remaining_time":3.556985151},
{"learn":[9.690174082],"iteration":18,"passed_time":0.06555384327,"remaining_time":3.384648434},
{"learn":[9.506034866],"iteration":19,"passed_time":0.06598315375,"remaining_time":3.233174534},
{"learn":[9.338524633],"iteration":20,"passed_time":0.06641950552,"remaining_time":3.096414091},
{"learn":[9.170203312],"iteration":21,"passed_time":0.06682527558,"remaining_time":2.970687251},
{"learn":[9.010299969],"iteration":22,"passed_time":0.06722150449,"remaining_time":2.855452604},
{"learn":[8.843866678],"iteration":23,"passed_time":0.06752523831,"remaining_time":2.746026358},
{"learn":[8.690548059],"iteration":24,"passed_time":0.06796446493,"remaining_time":2.650614132},
{"learn":[8.555307687],"iteration":25,"passed_time":0.06826078249,"remaining_time":2.557153929},
{"learn":[8.413851302],"iteration":26,"passed_time":0.06867767696,"remaining_time":2.474939988},
{"learn":[8.29256019],"iteration":27,"passed_time":0.06896716155,"remaining_time":2.394145751},
{"learn":[8.162193833],"iteration":28,"passed_time":0.06928472797,"remaining_time":2.319843823},
{"learn":[8.040736294],"iteration":29,"passed_time":0.06958779517,"remaining_time":2.250005377},
{"learn":[7.921220278],"iteration":30,"passed_time":0.06987557152,"remaining_time":2.184175123},
{"learn":[7.809589039],"iteration":31,"passed_time":0.07015030689,"remaining_time":2.122046783},
{"learn":[7.699675801],"iteration":32,"passed_time":0.07043899985,"remaining_time":2.064076147},
{"learn":[7.60645267],"iteration":33,"passed_time":0.07074010882,"remaining_time":2.009851327},
{"learn":[7.498880302],"iteration":34,"passed_time":0.07105300883,"remaining_time":1.959032958},
{"learn":[7.401158744],"iteration":35,"passed_time":0.07135057632,"remaining_time":1.910609877},
{"learn":[7.306431077],"iteration":36,"passed_time":0.07165560175,"remaining_time":1.864982283},
{"learn":[7.223863468],"iteration":37,"passed_time":0.07194291979,"remaining_time":1.821291811},
{"learn":[7.143477682],"iteration":38,"passed_time":0.07224736191,"remaining_time":1.780249097},
{"learn":[7.062817131],"iteration":39,"passed_time":0.07261096755,"remaining_time":1.742663221},
{"learn":[6.990793435],"iteration":40,"passed_time":0.07287974491,"remaining_time":1.704675009},
{"learn":[6.931862224],"iteration":41,"passed_time":0.07315452195,"remaining_time":1.66861981},
{"learn":[6.858296558],"iteration":42,"passed_time":0.07344267327,"remaining_time":1.634526473},
{"learn":[6.786268161],"iteration":43,"passed_time":0.07375224012,"remaining_time":1.602435035},
{"learn":[6.717118549],"iteration":44,"passed_time":0.07404039145,"remaining_time":1.571301641},
{"learn":[6.652948106],"iteration":45,"passed_time":0.0744113717,"remaining_time":1.543227144},
{"learn":[6.589686076],"iteration":46,"passed_time":0.07470339782,"remaining_time":1.514730598},
{"learn":[6.531283097],"iteration":47,"passed_time":0.07497584165,"remaining_time":1.487020859},
{"learn":[6.471368031],"iteration":48,"passed_time":0.07525553509,"remaining_time":1.460571712},
{"learn":[6.416481395],"iteration":49,"passed_time":0.07554597796,"remaining_time":1.435373581},
{"learn":[6.369870822],"iteration":50,"passed_time":0.07584175388,"remaining_time":1.411251459},
{"learn":[6.325678067],"iteration":51,"passed_time":0.07610944796,"remaining_time":1.387533782},
{"learn":[6.275766122],"iteration":52,"passed_time":0.07636780921,"remaining_time":1.364534251},
{"learn":[6.224773967],"iteration":53,"passed_time":0.07667700108,"remaining_time":1.343267463},
{"learn":[6.182249254],"iteration":54,"passed_time":0.07699119268,"remaining_time":1.322848674},
{"learn":[6.139904173],"iteration":55,"passed_time":0.0772538037,"remaining_time":1.302278405},
{"learn":[6.100525536],"iteration":56,"passed_time":0.07761340956,"remaining_time":1.284025355},
{"learn":[6.062568564],"iteration":57,"passed_time":0.07790822719,"remaining_time":1.265337069},
{"learn":[6.030559288],"iteration":58,"passed_time":0.07819592021,"remaining_time":1.24715866},
{"learn":[5.997931376],"iteration":59,"passed_time":0.07846557252,"remaining_time":1.22929397},
{"learn":[5.964103835],"iteration":60,"passed_time":0.07875322387,"remaining_time":1.212283233},
{"learn":[5.933729724],"iteration":61,"passed_time":0.07906558224,"remaining_time":1.196185744},
{"learn":[5.901932711],"iteration":62,"passed_time":0.07937581573,"remaining_time":1.180557767},
{"learn":[5.873727795],"iteration":63,"passed_time":0.07963551023,"remaining_time":1.164669337},
{"learn":[5.846485734],"iteration":64,"passed_time":0.07990799573,"remaining_time":1.149445785},
{"learn":[5.820630862],"iteration":65,"passed_time":0.08017235665,"remaining_time":1.13456032},
{"learn":[5.793646238],"iteration":66,"passed_time":0.08043642593,"remaining_time":1.120107245},
{"learn":[5.765388646],"iteration":67,"passed_time":0.08075599225,"remaining_time":1.106832129},
{"learn":[5.747073912],"iteration":68,"passed_time":0.08125796552,"remaining_time":1.096393709},
{"learn":[5.722315217],"iteration":69,"passed_time":0.08153853392,"remaining_time":1.083297665},
{"learn":[5.699970599],"iteration":70,"passed_time":0.08177760452,"remaining_time":1.070019642},
{"learn":[5.682732647],"iteration":71,"passed_time":0.08202513301,"remaining_time":1.057212825},
{"learn":[5.663525791],"iteration":72,"passed_time":0.08227249484,"remaining_time":1.044747982},
{"learn":[5.642381613],"iteration":73,"passed_time":0.08255077169,"remaining_time":1.033000197},
{"learn":[5.621404779],"iteration":74,"passed_time":0.08284533934,"remaining_time":1.021759185},
{"learn":[5.602460129],"iteration":75,"passed_time":0.08311140851,"remaining_time":1.010459756},
{"learn":[5.587337574],"iteration":76,"passed_time":0.08338139414,"remaining_time":0.9994938544},
{"learn":[5.572393026],"iteration":77,"passed_time":0.08364350518,"remaining_time":0.9887091254},
{"learn":[5.558425806],"iteration":78,"passed_time":0.08389186696,"remaining_time":0.9780304996},
{"learn":[5.541518902],"iteration":79,"passed_time":0.08415518628,"remaining_time":0.9677846422},
{"learn":[5.526157283],"iteration":80,"passed_time":0.08441404749,"remaining_time":0.957734687},
{"learn":[5.511746977],"iteration":81,"passed_time":0.08465657625,"remaining_time":0.9477406951},
{"learn":[5.504975022],"iteration":82,"passed_time":0.08476407053,"remaining_time":0.9364897912},
{"learn":[5.493980522],"iteration":83,"passed_time":0.08507084586,"remaining_time":0.9276773191},
{"learn":[5.480745463],"iteration":84,"passed_time":0.085349956,"remaining_time":0.9187671734},
{"learn":[5.464052013],"iteration":85,"passed_time":0.08561565019,"remaining_time":0.9099151659},
{"learn":[5.449143727],"iteration":86,"passed_time":0.08587309481,"remaining_time":0.901173972},
{"learn":[5.438255432],"iteration":87,"passed_time":0.08611295704,"remaining_time":0.892443373},
{"learn":[5.425927931],"iteration":88,"passed_time":0.08645831366,"remaining_time":0.8849834128},
{"learn":[5.412331217],"iteration":89,"passed_time":0.08670405057,"remaining_time":0.8766742891},
{"learn":[5.400691499],"iteration":90,"passed_time":0.08698578558,"remaining_time":0.868901968},
{"learn":[5.391618744],"iteration":91,"passed_time":0.08725243805,"remaining_time":0.8611436277},
{"learn":[5.380766572],"iteration":92,"passed_time":0.08750888273,"remaining_time":0.8534468455},
{"learn":[5.372207183],"iteration":93,"passed_time":0.08775282807,"remaining_time":0.8457878961},
{"learn":[5.362918837],"iteration":94,"passed_time":0.08803497972,"remaining_time":0.8386490173},
{"learn":[5.348292324],"iteration":95,"passed_time":0.08836483716,"remaining_time":0.8321022165},
{"learn":[5.339772295],"iteration":96,"passed_time":0.0885849921,"remaining_time":0.8246623491},
{"learn":[5.331515983],"iteration":97,"passed_time":0.08893480681,"remaining_time":0.8185632219},
{"learn":[5.323861644],"iteration":98,"passed_time":0.08919370969,"remaining_time":0.8117528529},
{"learn":[5.313277281],"iteration":99,"passed_time":0.089419656,"remaining_time":0.804776904},
{"learn":[5.30685627],"iteration":100,"passed_time":0.08964643559,"remaining_time":0.7979420356},
{"learn":[5.29652059],"iteration":101,"passed_time":0.08988517288,"remaining_time":0.7913420122},
{"learn":[5.288350766],"iteration":102,"passed_time":0.09013028483,"remaining_time":0.7849210242},
{"learn":[5.27993346],"iteration":103,"passed_time":0.09044439311,"remaining_time":0.7792132329},
{"learn":[5.271789139],"iteration":104,"passed_time":0.09070108777,"remaining_time":0.7731187958},
{"learn":[5.262684686],"iteration":105,"passed_time":0.09095832408,"remaining_time":0.7671390729},
{"learn":[5.251619772],"iteration":106,"passed_time":0.09121560205,"remaining_time":0.7612666601},
{"learn":[5.241012171],"iteration":107,"passed_time":0.09150117018,"remaining_time":0.755731887},
{"learn":[5.232684032],"iteration":108,"passed_time":0.09179394626,"remaining_time":0.7503523497},
{"learn":[5.224267141],"iteration":109,"passed_time":0.09206197365,"remaining_time":0.7448650596},
{"learn":[5.216324968],"iteration":110,"passed_time":0.09235095827,"remaining_time":0.7396396568},
{"learn":[5.211102527],"iteration":111,"passed_time":0.09260573637,"remaining_time":0.7342311955},
{"learn":[5.206364257],"iteration":112,"passed_time":0.09288138836,"remaining_time":0.7290778007},
{"learn":[5.196937641],"iteration":113,"passed_time":0.09317103961,"remaining_time":0.7241187815},
{"learn":[5.190746047],"iteration":114,"passed_time":0.09342769261,"remaining_time":0.7189870257},
{"learn":[5.181885213],"iteration":115,"passed_time":0.09372555175,"remaining_time":0.7142533427},
{"learn":[5.178293568],"iteration":116,"passed_time":0.09390766706,"remaining_time":0.7087219659},
{"learn":[5.170991438],"iteration":117,"passed_time":0.09424377416,"remaining_time":0.7044322781},
{"learn":[5.166257212],"iteration":118,"passed_time":0.09451600967,"remaining_time":0.6997361724},
{"learn":[5.161421246],"iteration":119,"passed_time":0.09477524587,"remaining_time":0.6950184697},
{"learn":[5.158223542],"iteration":120,"passed_time":0.0950138165,"remaining_time":0.6902243364},
{"learn":[5.15470988],"iteration":121,"passed_time":0.09517634951,"remaining_time":0.6849576629},
{"learn":[5.146388143],"iteration":122,"passed_time":0.09542946104,"remaining_time":0.6804198157},
{"learn":[5.139529364],"iteration":123,"passed_time":0.0957357364,"remaining_time":0.6763266539},
{"learn":[5.134276023],"iteration":124,"passed_time":0.09600034731,"remaining_time":0.6720024312},
{"learn":[5.128536065],"iteration":125,"passed_time":0.09627583264,"remaining_time":0.6678180772},
{"learn":[5.123300353],"iteration":126,"passed_time":0.09648173835,"remaining_time":0.6632169888},
{"learn":[5.116200518],"iteration":127,"passed_time":0.09692342317,"remaining_time":0.6602908203},
{"learn":[5.108728704],"iteration":128,"passed_time":0.09718640916,"remaining_time":0.6561966076},
{"learn":[5.104075866],"iteration":129,"passed_time":0.09745339495,"remaining_time":0.6521881047},
{"learn":[5.100317606],"iteration":130,"passed_time":0.09770204838,"remaining_time":0.6481151148},
{"learn":[5.095814182],"iteration":131,"passed_time":0.09800432395,"remaining_time":0.6444526757},
{"learn":[5.092146915],"iteration":132,"passed_time":0.09830697451,"remaining_time":0.6408432098},
{"learn":[5.085258329],"iteration":133,"passed_time":0.0985806266,"remaining_time":0.6370956913},
{"learn":[5.079219421],"iteration":134,"passed_time":0.09882578022,"remaining_time":0.6332170362},
{"learn":[5.076476829],"iteration":135,"passed_time":0.09910364043,"remaining_time":0.629599598},
{"learn":[5.072133867],"iteration":136,"passed_time":0.09947999539,"remaining_time":0.6266513578},
{"learn":[5.067031564],"iteration":137,"passed_time":0.09975864722,"remaining_time":0.6231301007},
{"learn":[5.061358312],"iteration":138,"passed_time":0.10005109,"remaining_time":0.6197409243},
{"learn":[5.056759124],"iteration":139,"passed_time":0.1003067847,"remaining_time":0.6161702489},
{"learn":[5.050254],"iteration":140,"passed_time":0.100582895,"remaining_time":0.6127709703},
{"learn":[5.048376474],"iteration":141,"passed_time":0.1006988472,"remaining_time":0.6084479638},
{"learn":[5.042603751],"iteration":142,"passed_time":0.1009538336,"remaining_time":0.6050170307},
{"learn":[5.037477349],"iteration":143,"passed_time":0.1011975289,"remaining_time":0.6015630887},
{"learn":[5.03230489],"iteration":144,"passed_time":0.1014621815,"remaining_time":0.5982770014},
{"learn":[5.025976187],"iteration":145,"passed_time":0.1017084601,"remaining_time":0.5949248281},
{"learn":[5.01952451],"iteration":146,"passed_time":0.1019750709,"remaining_time":0.5917328943},
{"learn":[5.017569424],"iteration":147,"passed_time":0.1022676386,"remaining_time":0.5887299197},
{"learn":[5.008962367],"iteration":148,"passed_time":0.1025637062,"remaining_time":0.5857833153},
{"learn":[5.003880266],"iteration":149,"passed_time":0.1028404831,"remaining_time":0.5827627378},
{"learn":[4.996387564],"iteration":150,"passed_time":0.1031092188,"remaining_time":0.57973329},
{"learn":[4.993361683],"iteration":151,"passed_time":0.1033712466,"remaining_time":0.5767027439},
{"learn":[4.99005752],"iteration":152,"passed_time":0.1036356075,"remaining_time":0.5737213041},
{"learn":[4.986908764],"iteration":153,"passed_time":0.1038743031,"remaining_time":0.5706341586},
{"learn":[4.985207175],"iteration":154,"passed_time":0.1040982078,"remaining_time":0.5675031331},
{"learn":[4.979003494],"iteration":155,"passed_time":0.104358069,"remaining_time":0.5646039118},
{"learn":[4.973142217],"iteration":156,"passed_time":0.1046257214,"remaining_time":0.5617801476},
{"learn":[4.967056696],"iteration":157,"passed_time":0.1049368299,"remaining_time":0.5592203212},
{"learn":[4.961460696],"iteration":158,"passed_time":0.1051840667,"remaining_time":0.556350944},
{"learn":[4.954240363],"iteration":159,"passed_time":0.1054883422,"remaining_time":0.5538137964},
{"learn":[4.952320707],"iteration":160,"passed_time":0.1056260015,"remaining_time":0.5504361197},
{"learn":[4.948337777],"iteration":161,"passed_time":0.1058653221,"remaining_time":0.5476243205},
{"learn":[4.943228639],"iteration":162,"passed_time":0.1061099757,"remaining_time":0.5448714705},
{"learn":[4.938545759],"iteration":163,"passed_time":0.1063637539,"remaining_time":0.5421957211},
{"learn":[4.935330572],"iteration":164,"passed_time":0.1066266149,"remaining_time":0.5395952936},
{"learn":[4.932051543],"iteration":165,"passed_time":0.1068904342,"remaining_time":0.5370278441},
{"learn":[4.928964153],"iteration":166,"passed_time":0.1071341712,"remaining_time":0.5343878121},
{"learn":[4.922860227],"iteration":167,"passed_time":0.1073776583,"remaining_time":0.5317750694},
{"learn":[4.917668772],"iteration":168,"passed_time":0.1076671012,"remaining_time":0.5294163377},
{"learn":[4.910365386],"iteration":169,"passed_time":0.1079294205,"remaining_time":0.5269495238},
{"learn":[4.906457206],"iteration":170,"passed_time":0.1082361125,"remaining_time":0.52472361},
{"learn":[4.901996508],"iteration":171,"passed_time":0.1084873492,"remaining_time":0.522253053},
{"learn":[4.896816173],"iteration":172,"passed_time":0.1087926246,"remaining_time":0.5200664771},
{"learn":[4.891123132],"iteration":173,"passed_time":0.1090734013,"remaining_time":0.5177852269},
{"learn":[4.887630202],"iteration":174,"passed_time":0.1093072222,"remaining_time":0.515305476},
{"learn":[4.885259712],"iteration":175,"passed_time":0.1095738747,"remaining_time":0.5130049586},
{"learn":[4.880659728],"iteration":176,"passed_time":0.1098868163,"remaining_time":0.5109426545},
{"learn":[4.877299723],"iteration":177,"passed_time":0.110199133,"remaining_time":0.50889712},
{"learn":[4.874038772],"iteration":178,"passed_time":0.1104712436,"remaining_time":0.5066865417},
{"learn":[4.86943698],"iteration":179,"passed_time":0.1107685194,"remaining_time":0.5046121439},
{"learn":[4.861268711],"iteration":180,"passed_time":0.1110888773,"remaining_time":0.5026618262},
{"learn":[4.858673056],"iteration":181,"passed_time":0.1113795285,"remaining_time":0.5005959029},
{"learn":[4.854036207],"iteration":182,"passed_time":0.1116265154,"remaining_time":0.498354443},
{"learn":[4.85130244],"iteration":183,"passed_time":0.1118918346,"remaining_time":0.4962159621},
{"learn":[4.847510084],"iteration":184,"passed_time":0.1122998545,"remaining_time":0.4947263862},
{"learn":[4.845691673],"iteration":185,"passed_time":0.1126497109,"remaining_time":0.4929938961},
{"learn":[4.842058646],"iteration":186,"passed_time":0.1129144468,"remaining_time":0.4909061244},
{"learn":[4.838623675],"iteration":187,"passed_time":0.1132088895,"remaining_time":0.4889660545},
{"learn":[4.834602161],"iteration":188,"passed_time":0.1134964158,"remaining_time":0.4870137208},
{"learn":[4.830858976],"iteration":189,"passed_time":0.1137677764,"remaining_time":0.485009994},
{"learn":[4.827590511],"iteration":190,"passed_time":0.1140059304,"remaining_time":0.4828837574},
{"learn":[4.822246226],"iteration":191,"passed_time":0.1142503757,"remaining_time":0.4808036643},
{"learn":[4.816686395],"iteration":192,"passed_time":0.1145214446,"remaining_time":0.478853916},
{"learn":[4.814797121],"iteration":193,"passed_time":0.1148005131,"remaining_time":0.4769547089},
{"learn":[4.811639392],"iteration":194,"passed_time":0.1150702904,"remaining_time":0.4750337628},
{"learn":[4.804813432],"iteration":195,"passed_time":0.115321027,"remaining_time":0.4730515598},
{"learn":[4.80251613],"iteration":196,"passed_time":0.1156958404,"remaining_time":0.4715926895},
{"learn":[4.800087884],"iteration":197,"passed_time":0.1160054489,"remaining_time":0.4698806567},
{"learn":[4.794773135],"iteration":198,"passed_time":0.116272143,"remaining_time":0.4680099828},
{"learn":[4.791664833],"iteration":199,"passed_time":0.1165192549,"remaining_time":0.4660770196},
{"learn":[4.785989873],"iteration":200,"passed_time":0.1167590755,"remaining_time":0.4641318472},
{"learn":[4.782387142],"iteration":201,"passed_time":0.1170567263,"remaining_time":0.4624320177},
{"learn":[4.778623704],"iteration":202,"passed_time":0.1173358781,"remaining_time":0.4606733735},
{"learn":[4.775772178],"iteration":203,"passed_time":0.1176412368,"remaining_time":0.4590314927},
{"learn":[4.77023101],"iteration":204,"passed_time":0.1179798855,"remaining_time":0.4575317509},
{"learn":[4.764496689],"iteration":205,"passed_time":0.1182743698,"remaining_time":0.4558730563},
{"learn":[4.763138716],"iteration":206,"passed_time":0.1185341476,"remaining_time":0.4540945848},
{"learn":[4.758053283],"iteration":207,"passed_time":0.1188222573,"remaining_time":0.452438595},
{"learn":[4.755063788],"iteration":208,"passed_time":0.1191324074,"remaining_time":0.4508791114},
{"learn":[4.752465267],"iteration":209,"passed_time":0.1194003098,"remaining_time":0.4491725942},
{"learn":[4.748067377],"iteration":210,"passed_time":0.1196589627,"remaining_time":0.4474451261},
{"learn":[4.744163298],"iteration":211,"passed_time":0.1198845757,"remaining_time":0.445608706},
{"learn":[4.736670896],"iteration":212,"passed_time":0.1201607277,"remaining_time":0.4439741441},
{"learn":[4.73349255],"iteration":213,"passed_time":0.1205521235,"remaining_time":0.4427755565},
{"learn":[4.731864595],"iteration":214,"passed_time":0.1207877776,"remaining_time":0.4410158393},
{"learn":[4.728398311],"iteration":215,"passed_time":0.1210553884,"remaining_time":0.4393862245},
{"learn":[4.723865975],"iteration":216,"passed_time":0.1214024116,"remaining_time":0.4380557063},
{"learn":[4.723483365],"iteration":217,"passed_time":0.1217202697,"remaining_time":0.4366295912},
{"learn":[4.72095416],"iteration":218,"passed_time":0.1220035046,"remaining_time":0.4350901236},
{"learn":[4.716173382],"iteration":219,"passed_time":0.1223172795,"remaining_time":0.4336703547},
{"learn":[4.710563974],"iteration":220,"passed_time":0.1226053892,"remaining_time":0.4321701275},
{"learn":[4.707160263],"iteration":221,"passed_time":0.1228749998,"remaining_time":0.4306159905},
{"learn":[4.70408351],"iteration":222,"passed_time":0.1231396941,"remaining_time":0.4290562435},
{"learn":[4.702501831],"iteration":223,"passed_time":0.1233915557,"remaining_time":0.4274636036},
{"learn":[4.700269738],"iteration":224,"passed_time":0.1236370426,"remaining_time":0.4258609245},
{"learn":[4.695346302],"iteration":225,"passed_time":0.1239901071,"remaining_time":0.4246386855},
{"learn":[4.689769299],"iteration":226,"passed_time":0.1242492184,"remaining_time":0.4231041665},
{"learn":[4.687919514],"iteration":227,"passed_time":0.1245324533,"remaining_time":0.4216625172},
{"learn":[4.682982074],"iteration":228,"passed_time":0.1247699823,"remaining_time":0.420077102},
{"learn":[4.679578702],"iteration":229,"passed_time":0.1251308797,"remaining_time":0.4189164235},
{"learn":[4.675751423],"iteration":230,"passed_time":0.1254100732,"remaining_time":0.4174906766},
{"learn":[4.672710726],"iteration":231,"passed_time":0.1256551852,"remaining_time":0.4159619923},
{"learn":[4.6690533],"iteration":232,"passed_time":0.1259224209,"remaining_time":0.4145171539},
{"learn":[4.667595702],"iteration":233,"passed_time":0.1262183218,"remaining_time":0.413176216},
{"learn":[4.664241291],"iteration":234,"passed_time":0.1264628505,"remaining_time":0.4116769389},
{"learn":[4.662246999],"iteration":235,"passed_time":0.1267133372,"remaining_time":0.410207583},
{"learn":[4.658668443],"iteration":236,"passed_time":0.1270183209,"remaining_time":0.4089239615},
{"learn":[4.658017572],"iteration":237,"passed_time":0.1273032641,"remaining_time":0.4075844001},
{"learn":[4.657656705],"iteration":238,"passed_time":0.1275885822,"remaining_time":0.4062548581},
{"learn":[4.653242871],"iteration":239,"passed_time":0.1280011436,"remaining_time":0.4053369547},
{"learn":[4.6507302],"iteration":240,"passed_time":0.1282863784,"remaining_time":0.4040222457},
{"learn":[4.647671336],"iteration":241,"passed_time":0.1285336153,"remaining_time":0.4025970263},
{"learn":[4.645506007],"iteration":242,"passed_time":0.1288035175,"remaining_time":0.4012521102},
{"learn":[4.641297906],"iteration":243,"passed_time":0.1290741698,"remaining_time":0.3999183294},
{"learn":[4.63798107],"iteration":244,"passed_time":0.1293690708,"remaining_time":0.3986679528},
{"learn":[4.635062318],"iteration":245,"passed_time":0.129658972,"remaining_time":0.3974100199},
{"learn":[4.631606017],"iteration":246,"passed_time":0.1299674556,"remaining_time":0.3962165751},
{"learn":[4.630215494],"iteration":247,"passed_time":0.1302688979,"remaining_time":0.3950089161},
{"learn":[4.62729814],"iteration":248,"passed_time":0.1305391751,"remaining_time":0.3937145403},
{"learn":[4.624691756],"iteration":249,"passed_time":0.1307829538,"remaining_time":0.3923488615},
{"learn":[4.621840053],"iteration":250,"passed_time":0.1310378153,"remaining_time":0.3910251937},
{"learn":[4.619602091],"iteration":251,"passed_time":0.131317467,"remaining_time":0.3897835926},
{"learn":[4.613584029],"iteration":252,"passed_time":0.1315894942,"remaining_time":0.3885270837},
{"learn":[4.6119388],"iteration":253,"passed_time":0.1318370227,"remaining_time":0.3872063738},
{"learn":[4.60870702],"iteration":254,"passed_time":0.1321085499,"remaining_time":0.3859641949},
{"learn":[4.604771557],"iteration":255,"passed_time":0.1323523703,"remaining_time":0.3846490761},
{"learn":[4.604231277],"iteration":256,"passed_time":0.1326103982,"remaining_time":0.3833833691},
{"learn":[4.600750354],"iteration":257,"passed_time":0.1329017577,"remaining_time":0.3822213341},
{"learn":[4.596488253],"iteration":258,"passed_time":0.1331340787,"remaining_time":0.3808971131},
{"learn":[4.59470784],"iteration":259,"passed_time":0.1333806489,"remaining_time":0.3796218468},
{"learn":[4.588818005],"iteration":260,"passed_time":0.1336269691,"remaining_time":0.3783537554},
{"learn":[4.585054174],"iteration":261,"passed_time":0.1338772891,"remaining_time":0.3771047303},
{"learn":[4.581471435],"iteration":262,"passed_time":0.1341189012,"remaining_time":0.3758388981},
{"learn":[4.577555199],"iteration":263,"passed_time":0.1343971781,"remaining_time":0.3746830419},
{"learn":[4.57457145],"iteration":264,"passed_time":0.1346702885,"remaining_time":0.3735194795},
{"learn":[4.573029224],"iteration":265,"passed_time":0.1349340662,"remaining_time":0.3723368593},
{"learn":[4.571326203],"iteration":266,"passed_time":0.1352414665,"remaining_time":0.3712808798},
{"learn":[4.571019224],"iteration":267,"passed_time":0.1354754123,"remaining_time":0.3700298576},
{"learn":[4.565766631],"iteration":268,"passed_time":0.1357091499,"remaining_time":0.3687858311},
{"learn":[4.563383471],"iteration":269,"passed_time":0.1359482622,"remaining_time":0.3675638199},
{"learn":[4.558165805],"iteration":270,"passed_time":0.1362682451,"remaining_time":0.3665666077},
{"learn":[4.55629209],"iteration":271,"passed_time":0.136640642,"remaining_time":0.3657146594},
{"learn":[4.549383848],"iteration":272,"passed_time":0.137034871,"remaining_time":0.3649243634},
{"learn":[4.546227503],"iteration":273,"passed_time":0.137347271,"remaining_time":0.3639201414},
{"learn":[4.540620977],"iteration":274,"passed_time":0.13758505,"remaining_time":0.3627242228},
{"learn":[4.532898237],"iteration":275,"passed_time":0.1378716181,"remaining_time":0.3616632301},
{"learn":[4.529757367],"iteration":276,"passed_time":0.1381460618,"remaining_time":0.360576183},
{"learn":[4.52579294],"iteration":277,"passed_time":0.1383947986,"remaining_time":0.3594282179},
{"learn":[4.521572155],"iteration":278,"passed_time":0.138674117,"remaining_time":0.358365729},
{"learn":[4.518818099],"iteration":279,"passed_time":0.1389365614,"remaining_time":0.3572654436},
{"learn":[4.514012334],"iteration":280,"passed_time":0.1391986724,"remaining_time":0.3561702686},
{"learn":[4.508331416],"iteration":281,"passed_time":0.1395149056,"remaining_time":0.3552188022},
{"learn":[4.506038537],"iteration":282,"passed_time":0.1398289306,"remaining_time":0.3542662304},
{"learn":[4.505805643],"iteration":283,"passed_time":0.1401140404,"remaining_time":0.3532452567},
{"learn":[4.501550352],"iteration":284,"passed_time":0.1403854843,"remaining_time":0.3521951623},
{"learn":[4.494692643],"iteration":285,"passed_time":0.1406290963,"remaining_time":0.3510810306},
{"learn":[4.489330245],"iteration":286,"passed_time":0.1408941655,"remaining_time":0.3500262718},
{"learn":[4.484826955],"iteration":287,"passed_time":0.1411534434,"remaining_time":0.3489626795},
{"learn":[4.478285428],"iteration":288,"passed_time":0.1414081798,"remaining_time":0.3478934804},
{"learn":[4.475311671],"iteration":289,"passed_time":0.1416632912,"remaining_time":0.3468308165},
{"learn":[4.471581298],"iteration":290,"passed_time":0.1418996953,"remaining_time":0.3457281236},
{"learn":[4.469164956],"iteration":291,"passed_time":0.1421593898,"remaining_time":0.3446878356},
{"learn":[4.462068024],"iteration":292,"passed_time":0.1424415831,"remaining_time":0.3437071648},
{"learn":[4.458540976],"iteration":293,"passed_time":0.1426852368,"remaining_time":0.342638698},
{"learn":[4.455757458],"iteration":294,"passed_time":0.1429357235,"remaining_time":0.3415921527},
{"learn":[4.453027414],"iteration":295,"passed_time":0.1432009177,"remaining_time":0.3405859664},
{"learn":[4.450659338],"iteration":296,"passed_time":0.1436938498,"remaining_time":0.3401238263},
{"learn":[4.444696901],"iteration":297,"passed_time":0.1439793346,"remaining_time":0.3391727949},
{"learn":[4.442052813],"iteration":298,"passed_time":0.144229113,"remaining_time":0.3381425023},
{"learn":[4.440036756],"iteration":299,"passed_time":0.1444835161,"remaining_time":0.3371282042},
{"learn":[4.435017051],"iteration":300,"passed_time":0.1447927496,"remaining_time":0.3362462857},
{"learn":[4.429962125],"iteration":301,"passed_time":0.1450556523,"remaining_time":0.3352610771},
{"learn":[4.427666256],"iteration":302,"passed_time":0.1453191799,"remaining_time":0.334282074},
{"learn":[4.425030004],"iteration":303,"passed_time":0.1455653335,"remaining_time":0.3332680004},
{"learn":[4.422588771],"iteration":304,"passed_time":0.1458468602,"remaining_time":0.3323395666},
{"learn":[4.418936667],"iteration":305,"passed_time":0.1460896806,"remaining_time":0.3313275762},
{"learn":[4.416887976],"iteration":306,"passed_time":0.1463697073,"remaining_time":0.3304045836},
{"learn":[4.413773354],"iteration":307,"passed_time":0.1466368181,"remaining_time":0.3294567472},
{"learn":[4.411129391],"iteration":308,"passed_time":0.1469159283,"remaining_time":0.3285401502},
{"learn":[4.40850819],"iteration":309,"passed_time":0.1472166622,"remaining_time":0.3276757966},
{"learn":[4.404880292],"iteration":310,"passed_time":0.1474672322,"remaining_time":0.3267039325},
{"learn":[4.404593827],"iteration":311,"passed_time":0.147727385,"remaining_time":0.3257578234},
{"learn":[4.402139942],"iteration":312,"passed_time":0.1480816995,"remaining_time":0.3250227718},
{"learn":[4.400284725],"iteration":313,"passed_time":0.1483496436,"remaining_time":0.3241014506},
{"learn":[4.395805521],"iteration":314,"passed_time":0.1486055466,"remaining_time":0.3231580935},
{"learn":[4.392838833],"iteration":315,"passed_time":0.1488583665,"remaining_time":0.3222124136},
{"learn":[4.389213061],"iteration":316,"passed_time":0.1491895572,"remaining_time":0.3214399608},
{"learn":[4.3861981],"iteration":317,"passed_time":0.1494611261,"remaining_time":0.320542415},
{"learn":[4.385054234],"iteration":318,"passed_time":0.149713821,"remaining_time":0.3196085018},
{"learn":[4.379364607],"iteration":319,"passed_time":0.1500066387,"remaining_time":0.3187641072},
{"learn":[4.378387619],"iteration":320,"passed_time":0.1503038312,"remaining_time":0.3179324031},
{"learn":[4.375816727],"iteration":321,"passed_time":0.1505717753,"remaining_time":0.3170424337},
{"learn":[4.374600202],"iteration":322,"passed_time":0.1508998411,"remaining_time":0.3162823296},
{"learn":[4.37098897],"iteration":323,"passed_time":0.1512421979,"remaining_time":0.3155547092},
{"learn":[4.367418484],"iteration":324,"passed_time":0.151566389,"remaining_time":0.314791731},
{"learn":[4.363584638],"iteration":325,"passed_time":0.1519023711,"remaining_time":0.3140558225},
{"learn":[4.360770706],"iteration":326,"passed_time":0.1521445665,"remaining_time":0.3131293373},
{"learn":[4.358675808],"iteration":327,"passed_time":0.1525599611,"remaining_time":0.3125618715},
{"learn":[4.354228195],"iteration":328,"passed_time":0.1528217388,"remaining_time":0.3116820266},
{"learn":[4.353773425],"iteration":329,"passed_time":0.1530959326,"remaining_time":0.3108311358},
{"learn":[4.351648009],"iteration":330,"passed_time":0.1533505023,"remaining_time":0.3099440667},
{"learn":[4.348209927],"iteration":331,"passed_time":0.1536426535,"remaining_time":0.3091364232},
{"learn":[4.345852733],"iteration":332,"passed_time":0.1538785159,"remaining_time":0.3082191294},
{"learn":[4.34237339],"iteration":333,"passed_time":0.1541122951,"remaining_time":0.3073017621},
{"learn":[4.340814362],"iteration":334,"passed_time":0.1543856139,"remaining_time":0.3064669649},
{"learn":[4.339707068],"iteration":335,"passed_time":0.1546888894,"remaining_time":0.30569471},
{"learn":[4.335430786],"iteration":336,"passed_time":0.1549461674,"remaining_time":0.3048347447},
{"learn":[4.33521887],"iteration":337,"passed_time":0.1552089034,"remaining_time":0.3039890357},
{"learn":[4.328507238],"iteration":338,"passed_time":0.1554944715,"remaining_time":0.3031912852},
{"learn":[4.326140732],"iteration":339,"passed_time":0.155774415,"remaining_time":0.302385629},
{"learn":[4.323785636],"iteration":340,"passed_time":0.1560693159,"remaining_time":0.3016119625},
{"learn":[4.320632534],"iteration":341,"passed_time":0.1563535091,"remaining_time":0.3008204942},
{"learn":[4.31973724],"iteration":342,"passed_time":0.156636994,"remaining_time":0.3000306271},
{"learn":[4.318000924],"iteration":343,"passed_time":0.1569266036,"remaining_time":0.2992553836},
{"learn":[4.312713628],"iteration":344,"passed_time":0.1571829233,"remaining_time":0.2984197529},
{"learn":[4.308220789],"iteration":345,"passed_time":0.1574386597,"remaining_time":0.2975863683},
{"learn":[4.305890947],"iteration":346,"passed_time":0.1577094786,"remaining_time":0.2967846961},
{"learn":[4.305137856],"iteration":347,"passed_time":0.1579807558,"remaining_time":0.2959869333},
{"learn":[4.304787172],"iteration":348,"passed_time":0.1582496582,"remaining_time":0.2951877578},
{"learn":[4.30350134],"iteration":349,"passed_time":0.158522977,"remaining_time":0.2943998144},
{"learn":[4.30293809],"iteration":350,"passed_time":0.1587886295,"remaining_time":0.2936006283},
{"learn":[4.299548459],"iteration":351,"passed_time":0.1592450635,"remaining_time":0.2931556851},
{"learn":[4.294768408],"iteration":352,"passed_time":0.1595022582,"remaining_time":0.2923454987},
{"learn":[4.294581479],"iteration":353,"passed_time":0.1598418651,"remaining_time":0.2916888272},
{"learn":[4.292551604],"iteration":354,"passed_time":0.1601065177,"remaining_time":0.2908977574},
{"learn":[4.288628894],"iteration":355,"passed_time":0.1603855028,"remaining_time":0.2901355725},
{"learn":[4.287802767],"iteration":356,"passed_time":0.1606153656,"remaining_time":0.2892876192},
{"learn":[4.284566905],"iteration":357,"passed_time":0.1610212606,"remaining_time":0.288758797},
{"learn":[4.27890232],"iteration":358,"passed_time":0.1613293276,"remaining_time":0.288055986},
{"learn":[4.276938023],"iteration":359,"passed_time":0.1615807308,"remaining_time":0.2872546326},
{"learn":[4.273425094],"iteration":360,"passed_time":0.1618515081,"remaining_time":0.2864906196},
{"learn":[4.269726505],"iteration":361,"passed_time":0.1628681206,"remaining_time":0.2870438148},
{"learn":[4.265565857],"iteration":362,"passed_time":0.1631668131,"remaining_time":0.2863285397},
{"learn":[4.262117173],"iteration":363,"passed_time":0.1635023785,"remaining_time":0.2856799801},
{"learn":[4.259185148],"iteration":364,"passed_time":0.1637723225,"remaining_time":0.284918972},
{"learn":[4.257668507],"iteration":365,"passed_time":0.1640217675,"remaining_time":0.2841251383},
{"learn":[4.253432436],"iteration":366,"passed_time":0.1643143353,"remaining_time":0.2834086492},
{"learn":[4.250216667],"iteration":367,"passed_time":0.1646100696,"remaining_time":0.2826999021},
{"learn":[4.24514828],"iteration":368,"passed_time":0.1649847579,"remaining_time":0.2821284072},
{"learn":[4.244015772],"iteration":369,"passed_time":0.165239911,"remaining_time":0.2813544431},
{"learn":[4.240329192],"iteration":370,"passed_time":0.1655060635,"remaining_time":0.2806019244},
{"learn":[4.236718014],"iteration":371,"passed_time":0.1657864236,"remaining_time":0.2798760054},
{"learn":[4.233495944],"iteration":372,"passed_time":0.1660312856,"remaining_time":0.2790928044},
{"learn":[4.230357491],"iteration":373,"passed_time":0.1663100207,"remaining_time":0.2783691791},
{"learn":[4.227381215],"iteration":374,"passed_time":0.1665776315,"remaining_time":0.2776293858},
{"learn":[4.226169067],"iteration":375,"passed_time":0.1668633663,"remaining_time":0.2769221823},
{"learn":[4.225963861],"iteration":376,"passed_time":0.1671161861,"remaining_time":0.2761628222},
{"learn":[4.224346548],"iteration":377,"passed_time":0.1673388409,"remaining_time":0.2753565055},
{"learn":[4.222595381],"iteration":378,"passed_time":0.1675969105,"remaining_time":0.2746112967},
{"learn":[4.219700938],"iteration":379,"passed_time":0.1678352312,"remaining_time":0.2738364298},
{"learn":[4.216356207],"iteration":380,"passed_time":0.1680994671,"remaining_time":0.2731064833},
{"learn":[4.214326494],"iteration":381,"passed_time":0.1684026176,"remaining_time":0.2724419312},
{"learn":[4.212901398],"iteration":382,"passed_time":0.1687506824,"remaining_time":0.2718516216},
{"learn":[4.211331091],"iteration":383,"passed_time":0.1690139601,"remaining_time":0.271126561},
{"learn":[4.208624791],"iteration":384,"passed_time":0.1692740296,"remaining_time":0.2703987745},
{"learn":[4.204659106],"iteration":385,"passed_time":0.1695328491,"remaining_time":0.2696714232},
{"learn":[4.202968852],"iteration":386,"passed_time":0.1697882939,"remaining_time":0.2689411476},
{"learn":[4.197261935],"iteration":387,"passed_time":0.170042572,"remaining_time":0.2682114795},
{"learn":[4.196934403],"iteration":388,"passed_time":0.1703076829,"remaining_time":0.2675012705},
{"learn":[4.192479929],"iteration":389,"passed_time":0.1705917928,"remaining_time":0.2668230605},
{"learn":[4.190243116],"iteration":390,"passed_time":0.1708663615,"remaining_time":0.2661320055},
{"learn":[4.185852431],"iteration":391,"passed_time":0.1711236394,"remaining_time":0.2654162571},
{"learn":[4.180967944],"iteration":392,"passed_time":0.1713849589,"remaining_time":0.264709084},
{"learn":[4.178283162],"iteration":393,"passed_time":0.1716292792,"remaining_time":0.2639780284},
{"learn":[4.176341157],"iteration":394,"passed_time":0.1719168472,"remaining_time":0.2633156774},
{"learn":[4.176041504],"iteration":395,"passed_time":0.1722889524,"remaining_time":0.2627841597},
{"learn":[4.175564513],"iteration":396,"passed_time":0.1725963944,"remaining_time":0.2621552287},
{"learn":[4.170830274],"iteration":397,"passed_time":0.1728568388,"remaining_time":0.2614568266},
{"learn":[4.167804808],"iteration":398,"passed_time":0.1731279077,"remaining_time":0.2607766229},
{"learn":[4.165860548],"iteration":399,"passed_time":0.1733742696,"remaining_time":0.2600614044},
{"learn":[4.160950571],"iteration":400,"passed_time":0.1736311309,"remaining_time":0.2593642081},
{"learn":[4.158544115],"iteration":401,"passed_time":0.173855119,"remaining_time":0.2586203014},
{"learn":[4.154448767],"iteration":402,"passed_time":0.1741265629,"remaining_time":0.2579492756},
{"learn":[4.15197457],"iteration":403,"passed_time":0.1743731748,"remaining_time":0.2572435945},
{"learn":[4.149562679],"iteration":404,"passed_time":0.1746058707,"remaining_time":0.256519736},
{"learn":[4.149327961],"iteration":405,"passed_time":0.174976726,"remaining_time":0.2560004316},
{"learn":[4.147444889],"iteration":406,"passed_time":0.1752297958,"remaining_time":0.2553102431},
{"learn":[4.147254809],"iteration":407,"passed_time":0.1754926152,"remaining_time":0.2546363436},
{"learn":[4.144589165],"iteration":408,"passed_time":0.1757819748,"remaining_time":0.2540028046},
{"learn":[4.141691034],"iteration":409,"passed_time":0.1760817505,"remaining_time":0.2533859336},
{"learn":[4.138893468],"iteration":410,"passed_time":0.1763696935,"remaining_time":0.2527536483},
{"learn":[4.136964597],"iteration":411,"passed_time":0.1766385125,"remaining_time":0.2520957411},
{"learn":[4.133773523],"iteration":412,"passed_time":0.1768831245,"remaining_time":0.2514053125},
{"learn":[4.131363444],"iteration":413,"passed_time":0.1771440689,"remaining_time":0.2507401555},
{"learn":[4.130228592],"iteration":414,"passed_time":0.1773948056,"remaining_time":0.2500625572},
{"learn":[4.12884186],"iteration":415,"passed_time":0.177650292,"remaining_time":0.2493936791},
{"learn":[4.12413494],"iteration":416,"passed_time":0.1778960705,"remaining_time":0.2487132113},
{"learn":[4.119422508],"iteration":417,"passed_time":0.1782859665,"remaining_time":0.2482354844},
{"learn":[4.117038244],"iteration":418,"passed_time":0.1785586186,"remaining_time":0.2475956024},
{"learn":[4.116067631],"iteration":419,"passed_time":0.1788413536,"remaining_time":0.246971393},
{"learn":[4.110343455],"iteration":420,"passed_time":0.1790984232,"remaining_time":0.2463135084},
{"learn":[4.105604544],"iteration":421,"passed_time":0.1793490765,"remaining_time":0.2456487351},
{"learn":[4.103390131],"iteration":422,"passed_time":0.1796072711,"remaining_time":0.2449962067},
{"learn":[4.096724402],"iteration":423,"passed_time":0.1798575495,"remaining_time":0.2443347842},
{"learn":[4.093431279],"iteration":424,"passed_time":0.1801404927,"remaining_time":0.2437194902},
{"learn":[4.091412744],"iteration":425,"passed_time":0.1803893961,"remaining_time":0.2430598906},
{"learn":[4.091192901],"iteration":426,"passed_time":0.1806562153,"remaining_time":0.2424262561},
{"learn":[4.088994581],"iteration":427,"passed_time":0.1809291591,"remaining_time":0.241802521},
{"learn":[4.087845355],"iteration":428,"passed_time":0.1811855204,"remaining_time":0.24115835},
{"learn":[4.083650279],"iteration":429,"passed_time":0.1814769632,"remaining_time":0.2405624861},
{"learn":[4.079840652],"iteration":430,"passed_time":0.1817419075,"remaining_time":0.2399330518},
{"learn":[4.075707828],"iteration":431,"passed_time":0.1820094349,"remaining_time":0.2393087014},
{"learn":[4.071345409],"iteration":432,"passed_time":0.1822440474,"remaining_time":0.2386428981},
{"learn":[4.067460475],"iteration":433,"passed_time":0.1825148663,"remaining_time":0.2380263003},
{"learn":[4.064914749],"iteration":434,"passed_time":0.1827603116,"remaining_time":0.2373783357},
{"learn":[4.063823175],"iteration":435,"passed_time":0.1831140844,"remaining_time":0.2368723477},
{"learn":[4.058898471],"iteration":436,"passed_time":0.1833664043,"remaining_time":0.2362363515},
{"learn":[4.054120355],"iteration":437,"passed_time":0.1836302236,"remaining_time":0.2356168622},
{"learn":[4.052715901],"iteration":438,"passed_time":0.183879002,"remaining_time":0.2349797725},
{"learn":[4.052114167],"iteration":439,"passed_time":0.1841229057,"remaining_time":0.2343382436},
{"learn":[4.051377267],"iteration":440,"passed_time":0.1843719341,"remaining_time":0.233705014},
{"learn":[4.049275336],"iteration":441,"passed_time":0.1846498776,"remaining_time":0.2331100265},
{"learn":[4.047099198],"iteration":442,"passed_time":0.1849317376,"remaining_time":0.2325213947},
{"learn":[4.044348685],"iteration":443,"passed_time":0.1852099728,"remaining_time":0.2319296056},
{"learn":[4.042822379],"iteration":444,"passed_time":0.1854586263,"remaining_time":0.2313023316},
{"learn":[4.041258611],"iteration":445,"passed_time":0.1857300701,"remaining_time":0.2307050647},
{"learn":[4.040044254],"iteration":446,"passed_time":0.1860053055,"remaining_time":0.2301139462},
{"learn":[4.036860137],"iteration":447,"passed_time":0.1862655416,"remaining_time":0.2295057566},
{"learn":[4.036372284],"iteration":448,"passed_time":0.1865068204,"remaining_time":0.2288758532},
{"learn":[4.03368231],"iteration":449,"passed_time":0.1867895971,"remaining_time":0.2282983964},
{"learn":[4.032439519],"iteration":450,"passed_time":0.1870455834,"remaining_time":0.2276896348},
{"learn":[4.032008634],"iteration":451,"passed_time":0.1874366459,"remaining_time":0.2272461991},
{"learn":[4.030034932],"iteration":452,"passed_time":0.1877275471,"remaining_time":0.2266820492},
{"learn":[4.028173412],"iteration":453,"passed_time":0.1879835752,"remaining_time":0.2260771631},
{"learn":[4.023806097],"iteration":454,"passed_time":0.1882929337,"remaining_time":0.2255376898},
{"learn":[4.020239186],"iteration":455,"passed_time":0.188562211,"remaining_time":0.2249514096},
{"learn":[4.017384838],"iteration":456,"passed_time":0.1888237388,"remaining_time":0.2243573089},
{"learn":[4.016468229],"iteration":457,"passed_time":0.1891020989,"remaining_time":0.22378458},
{"learn":[4.014530169],"iteration":458,"passed_time":0.1893937501,"remaining_time":0.2232287991},
{"learn":[4.012884822],"iteration":459,"passed_time":0.1896664439,"remaining_time":0.2226519124},
{"learn":[4.008924707],"iteration":460,"passed_time":0.1899263884,"remaining_time":0.2220614389},
{"learn":[4.008286778],"iteration":461,"passed_time":0.1902057902,"remaining_time":0.2214950544},
{"learn":[4.006444202],"iteration":462,"passed_time":0.1905878948,"remaining_time":0.2210490271},
{"learn":[4.003284363],"iteration":463,"passed_time":0.1908679216,"remaining_time":0.2204853577},
{"learn":[3.999811484],"iteration":464,"passed_time":0.1911259079,"remaining_time":0.2198975499},
{"learn":[3.997483319],"iteration":465,"passed_time":0.1915511352,"remaining_time":0.219502803},
{"learn":[3.99708333],"iteration":466,"passed_time":0.191880076,"remaining_time":0.2189980311},
{"learn":[3.995860263],"iteration":467,"passed_time":0.1921917261,"remaining_time":0.2184743553},
{"learn":[3.994131111],"iteration":468,"passed_time":0.1924804607,"remaining_time":0.2179256389},
{"learn":[3.993125499],"iteration":469,"passed_time":0.1927705286,"remaining_time":0.2173795323},
{"learn":[3.992954084],"iteration":470,"passed_time":0.1930378894,"remaining_time":0.2168090095},
{"learn":[3.990635743],"iteration":471,"passed_time":0.1932893343,"remaining_time":0.2162219672},
{"learn":[3.986678254],"iteration":472,"passed_time":0.193546279,"remaining_time":0.2156424715},
{"learn":[3.986393291],"iteration":473,"passed_time":0.1938422216,"remaining_time":0.215107613},
{"learn":[3.986152671],"iteration":474,"passed_time":0.1941676626,"remaining_time":0.2146063639},
{"learn":[3.985596662],"iteration":475,"passed_time":0.194504103,"remaining_time":0.2141179621},
{"learn":[3.983853457],"iteration":476,"passed_time":0.194804337,"remaining_time":0.2135904995},
{"learn":[3.983263928],"iteration":477,"passed_time":0.1950647815,"remaining_time":0.2130205354},
{"learn":[3.980067202],"iteration":478,"passed_time":0.1953460582,"remaining_time":0.2124745226},
{"learn":[3.978115407],"iteration":479,"passed_time":0.1956067526,"remaining_time":0.2119073154},
{"learn":[3.972661644],"iteration":480,"passed_time":0.1958538645,"remaining_time":0.211326727},
{"learn":[3.969938254],"iteration":481,"passed_time":0.1961459739,"remaining_time":0.2107958807},
{"learn":[3.968211434],"iteration":482,"passed_time":0.1963848779,"remaining_time":0.2102090722},
{"learn":[3.966113368],"iteration":483,"passed_time":0.1966670712,"remaining_time":0.2096698528},
{"learn":[3.962246044],"iteration":484,"passed_time":0.1969190161,"remaining_time":0.2090995738},
{"learn":[3.961319703],"iteration":485,"passed_time":0.1971682945,"remaining_time":0.2085277847},
{"learn":[3.96078191],"iteration":486,"passed_time":0.1974616955,"remaining_time":0.2080037984},
{"learn":[3.958913633],"iteration":487,"passed_time":0.1976945165,"remaining_time":0.2074171976},
{"learn":[3.957428286],"iteration":488,"passed_time":0.1980690799,"remaining_time":0.2069801632},
{"learn":[3.952641965],"iteration":489,"passed_time":0.1983272328,"remaining_time":0.2064222219},
{"learn":[3.951486786],"iteration":490,"passed_time":0.198592052,"remaining_time":0.2058724124},
{"learn":[3.94938344],"iteration":491,"passed_time":0.1989219095,"remaining_time":0.2053909147},
{"learn":[3.947297924],"iteration":492,"passed_time":0.1992721408,"remaining_time":0.2049309846},
{"learn":[3.946284886],"iteration":493,"passed_time":0.1995120864,"remaining_time":0.2043585338},
{"learn":[3.943288204],"iteration":494,"passed_time":0.1997795305,"remaining_time":0.2038154806},
{"learn":[3.943076488],"iteration":495,"passed_time":0.2000176428,"remaining_time":0.2032437338},
{"learn":[3.942347078],"iteration":496,"passed_time":0.2002795039,"remaining_time":0.2026973651},
{"learn":[3.940251541],"iteration":497,"passed_time":0.2005599056,"remaining_time":0.2021708285},
{"learn":[3.939011019],"iteration":498,"passed_time":0.2008153087,"remaining_time":0.2016201796},
{"learn":[3.938760512],"iteration":499,"passed_time":0.2010875442,"remaining_time":0.2010875442},
{"learn":[3.934522727],"iteration":500,"passed_time":0.2013853617,"remaining_time":0.2005814281},
{"learn":[3.930091193],"iteration":501,"passed_time":0.201692512,"remaining_time":0.2000854003},
{"learn":[3.927671752],"iteration":502,"passed_time":0.2019274578,"remaining_time":0.1995187804},
{"learn":[3.927280041],"iteration":503,"passed_time":0.2021951519,"remaining_time":0.198985705},
{"learn":[3.925987561],"iteration":504,"passed_time":0.2024591378,"remaining_time":0.198450046},
{"learn":[3.921645957],"iteration":505,"passed_time":0.2027089578,"remaining_time":0.1979016308},
{"learn":[3.920333743],"iteration":506,"passed_time":0.202956028,"remaining_time":0.1973517196},
{"learn":[3.918659461],"iteration":507,"passed_time":0.2032149309,"remaining_time":0.1968144606},
{"learn":[3.916124385],"iteration":508,"passed_time":0.2034487935,"remaining_time":0.1962541406},
{"learn":[3.913849268],"iteration":509,"passed_time":0.2037100712,"remaining_time":0.195721441},
{"learn":[3.912826119],"iteration":510,"passed_time":0.2039671409,"remaining_time":0.1951857767},
{"learn":[3.910034145],"iteration":511,"passed_time":0.2042470426,"remaining_time":0.1946729625},
{"learn":[3.90792379],"iteration":512,"passed_time":0.2045142784,"remaining_time":0.1941490323},
{"learn":[3.907823851],"iteration":513,"passed_time":0.2047560155,"remaining_time":0.1936019913},
{"learn":[3.904527401],"iteration":514,"passed_time":0.2051009138,"remaining_time":0.1931532878},
{"learn":[3.903378283],"iteration":515,"passed_time":0.2053789824,"remaining_time":0.1926423013},
{"learn":[3.902170135],"iteration":516,"passed_time":0.205629094,"remaining_time":0.1921060975},
{"learn":[3.899435429],"iteration":517,"passed_time":0.2058721228,"remaining_time":0.1915644077},
{"learn":[3.897497505],"iteration":518,"passed_time":0.2062171044,"remaining_time":0.1911183569},
{"learn":[3.896426119],"iteration":519,"passed_time":0.2064616747,"remaining_time":0.1905800074},
{"learn":[3.896044669],"iteration":520,"passed_time":0.2067104948,"remaining_time":0.1900466929},
{"learn":[3.892795942],"iteration":521,"passed_time":0.206970106,"remaining_time":0.1895243499},
{"learn":[3.892413888],"iteration":522,"passed_time":0.2073288369,"remaining_time":0.1890934134},
{"learn":[3.891738985],"iteration":523,"passed_time":0.207608197,"remaining_time":0.1885906523},
{"learn":[3.88822057],"iteration":524,"passed_time":0.2078629751,"remaining_time":0.1880665013},
{"learn":[3.883837053],"iteration":525,"passed_time":0.2081433352,"remaining_time":0.1875664275},
{"learn":[3.881769742],"iteration":526,"passed_time":0.208440986,"remaining_time":0.1870827066},
{"learn":[3.880356898],"iteration":527,"passed_time":0.2087009722,"remaining_time":0.1865660206},
{"learn":[3.879250273],"iteration":528,"passed_time":0.2089652914,"remaining_time":0.1860541631},
{"learn":[3.877174493],"iteration":529,"passed_time":0.2092124866,"remaining_time":0.1855280542},
{"learn":[3.875854201],"iteration":530,"passed_time":0.2094418077,"remaining_time":0.1849872087},
{"learn":[3.873189396],"iteration":531,"passed_time":0.2097452916,"remaining_time":0.1845127753},
{"learn":[3.871583368],"iteration":532,"passed_time":0.2099931117,"remaining_time":0.1839902123},
{"learn":[3.869622679],"iteration":533,"passed_time":0.2102470149,"remaining_time":0.1834739868},
{"learn":[3.866860164],"iteration":534,"passed_time":0.2104901686,"remaining_time":0.1829493989},
{"learn":[3.864498444],"iteration":535,"passed_time":0.2107687787,"remaining_time":0.1824565547},
{"learn":[3.861416322],"iteration":536,"passed_time":0.2110109325,"remaining_time":0.1819330759},
{"learn":[3.860265769],"iteration":537,"passed_time":0.2112537529,"remaining_time":0.1814112153},
{"learn":[3.859328725],"iteration":538,"passed_time":0.2115111976,"remaining_time":0.1809028981},
{"learn":[3.858521278],"iteration":539,"passed_time":0.2117546013,"remaining_time":0.1803835492},
{"learn":[3.85599111],"iteration":540,"passed_time":0.2120396694,"remaining_time":0.1799005698},
{"learn":[3.852379816],"iteration":541,"passed_time":0.2123498612,"remaining_time":0.1794395506},
{"learn":[3.851327537],"iteration":542,"passed_time":0.2126395125,"remaining_time":0.1789617996},
{"learn":[3.847854898],"iteration":543,"passed_time":0.2129112064,"remaining_time":0.1784696877},
{"learn":[3.847083414],"iteration":544,"passed_time":0.2131651928,"remaining_time":0.1779636014},
{"learn":[3.845397429],"iteration":545,"passed_time":0.213424929,"remaining_time":0.1774632194},
{"learn":[3.841933528],"iteration":546,"passed_time":0.2136808737,"remaining_time":0.1769605773},
{"learn":[3.840996474],"iteration":547,"passed_time":0.2141086426,"remaining_time":0.1766005592},
{"learn":[3.838355966],"iteration":548,"passed_time":0.2144002104,"remaining_time":0.176128406},
{"learn":[3.83342799],"iteration":549,"passed_time":0.2146976529,"remaining_time":0.175661716},
{"learn":[3.828161535],"iteration":550,"passed_time":0.2149721383,"remaining_time":0.175176933},
{"learn":[3.823502399],"iteration":551,"passed_time":0.2152440822,"remaining_time":0.1746908493},
{"learn":[3.820068862],"iteration":552,"passed_time":0.2155459827,"remaining_time":0.1742297546},
{"learn":[3.817951642],"iteration":553,"passed_time":0.2158740903,"remaining_time":0.1737903326},
{"learn":[3.815785958],"iteration":554,"passed_time":0.2161373263,"remaining_time":0.1732992976},
{"learn":[3.81503012],"iteration":555,"passed_time":0.2164412267,"remaining_time":0.1728415552},
{"learn":[3.813529315],"iteration":556,"passed_time":0.2166940466,"remaining_time":0.1723437391},
{"learn":[3.808881326],"iteration":557,"passed_time":0.2170015303,"remaining_time":0.171890101},
{"learn":[3.808740434],"iteration":558,"passed_time":0.2172889316,"remaining_time":0.1714211428},
{"learn":[3.80714352],"iteration":559,"passed_time":0.217582291,"remaining_time":0.1709575144},
{"learn":[3.80573346],"iteration":560,"passed_time":0.2178461936,"remaining_time":0.1704714421},
{"learn":[3.803370052],"iteration":561,"passed_time":0.21810218,"remaining_time":0.1699799908},
{"learn":[3.803215211],"iteration":562,"passed_time":0.2183639994,"remaining_time":0.1694939036},
{"learn":[3.801309667],"iteration":563,"passed_time":0.2186196524,"remaining_time":0.1690038448},
{"learn":[3.800003847],"iteration":564,"passed_time":0.2188567648,"remaining_time":0.1685003411},
{"learn":[3.798026138],"iteration":565,"passed_time":0.2191182092,"remaining_time":0.1680164361},
{"learn":[3.794745847],"iteration":566,"passed_time":0.2193781121,"remaining_time":0.1675321385},
{"learn":[3.794312041],"iteration":567,"passed_time":0.2196870956,"remaining_time":0.16708596},
{"learn":[3.792205926],"iteration":568,"passed_time":0.2199882879,"remaining_time":0.1666343622},
{"learn":[3.788991061],"iteration":569,"passed_time":0.2202475658,"remaining_time":0.1661516724},
{"learn":[3.787391572],"iteration":570,"passed_time":0.2205607158,"remaining_time":0.16571024},
{"learn":[3.7826445],"iteration":571,"passed_time":0.2208589915,"remaining_time":0.1652581265},
{"learn":[3.781700331],"iteration":572,"passed_time":0.2211464762,"remaining_time":0.1647985085},
{"learn":[3.780045374],"iteration":573,"passed_time":0.2213930464,"remaining_time":0.1643091251},
{"learn":[3.775462644],"iteration":574,"passed_time":0.2217486109,"remaining_time":0.1639011472},
{"learn":[3.773711943],"iteration":575,"passed_time":0.2220060971,"remaining_time":0.1634211548},
{"learn":[3.772415806],"iteration":576,"passed_time":0.2223029147,"remaining_time":0.1629707676},
{"learn":[3.770170875],"iteration":577,"passed_time":0.222583983,"remaining_time":0.1625094132},
{"learn":[3.765166479],"iteration":578,"passed_time":0.2228397611,"remaining_time":0.1620302926},
{"learn":[3.763976102],"iteration":579,"passed_time":0.2230861646,"remaining_time":0.1615451537},
{"learn":[3.760761708],"iteration":580,"passed_time":0.2233449425,"remaining_time":0.1610697606},
{"learn":[3.758155662],"iteration":581,"passed_time":0.2236419684,"remaining_time":0.1606225821},
{"learn":[3.756844548],"iteration":582,"passed_time":0.223892455,"remaining_time":0.1601426308},
{"learn":[3.753098923],"iteration":583,"passed_time":0.224175565,"remaining_time":0.1596867038},
{"learn":[3.751618946],"iteration":584,"passed_time":0.2244549668,"remaining_time":0.1592287371},
{"learn":[3.751398464],"iteration":585,"passed_time":0.2247227025,"remaining_time":0.158763138},
{"learn":[3.749920103],"iteration":586,"passed_time":0.2249601899,"remaining_time":0.1582769309},
{"learn":[3.748237465],"iteration":587,"passed_time":0.2252121348,"remaining_time":0.1578016999},
{"learn":[3.746021536],"iteration":588,"passed_time":0.2254604966,"remaining_time":0.1573247268},
{"learn":[3.74417648],"iteration":589,"passed_time":0.2257301489,"remaining_time":0.1568633238},
{"learn":[3.738788389],"iteration":590,"passed_time":0.2259956347,"remaining_time":0.1563996863},
{"learn":[3.736021611],"iteration":591,"passed_time":0.2262411633,"remaining_time":0.1559229639},
{"learn":[3.734546151],"iteration":592,"passed_time":0.2265130239,"remaining_time":0.155465094},
{"learn":[3.733527479],"iteration":593,"passed_time":0.2267759682,"remaining_time":0.155001756},
{"learn":[3.733026392],"iteration":594,"passed_time":0.227016997,"remaining_time":0.1545241745},
{"learn":[3.730314752],"iteration":595,"passed_time":0.227256026,"remaining_time":0.154046031},
{"learn":[3.727342596],"iteration":596,"passed_time":0.2275193036,"remaining_time":0.1535850576},
{"learn":[3.725459604],"iteration":597,"passed_time":0.227794539,"remaining_time":0.1531327837},
{"learn":[3.723158842],"iteration":598,"passed_time":0.228037401,"remaining_time":0.1526594287},
{"learn":[3.722362756],"iteration":599,"passed_time":0.2282855962,"remaining_time":0.1521903974},
{"learn":[3.721443615],"iteration":600,"passed_time":0.2285463323,"remaining_time":0.1517304269},
{"learn":[3.720743486],"iteration":601,"passed_time":0.2288244841,"remaining_time":0.1512826324},
{"learn":[3.720215334],"iteration":602,"passed_time":0.2290591383,"remaining_time":0.1508067627},
{"learn":[3.719436563],"iteration":603,"passed_time":0.2292951674,"remaining_time":0.1503325932},
{"learn":[3.715046574],"iteration":604,"passed_time":0.2295149057,"remaining_time":0.1498485748},
{"learn":[3.71443396],"iteration":605,"passed_time":0.2297620592,"remaining_time":0.149383253},
{"learn":[3.712938941],"iteration":606,"passed_time":0.2300402527,"remaining_time":0.1489387468},
{"learn":[3.712814764],"iteration":607,"passed_time":0.2303003222,"remaining_time":0.1484831025},
{"learn":[3.71235348],"iteration":608,"passed_time":0.2305573919,"remaining_time":0.1480261744},
{"learn":[3.711223749],"iteration":609,"passed_time":0.2308576676,"remaining_time":0.1475975252},
{"learn":[3.710755648],"iteration":610,"passed_time":0.2311380693,"remaining_time":0.1471566431},
{"learn":[3.708668039],"iteration":611,"passed_time":0.2313813897,"remaining_time":0.1466927765},
{"learn":[3.705623591],"iteration":612,"passed_time":0.2316362094,"remaining_time":0.1462368892},
{"learn":[3.704045802],"iteration":613,"passed_time":0.2319653586,"remaining_time":0.145828385},
{"learn":[3.699915209],"iteration":614,"passed_time":0.2322863832,"remaining_time":0.1454150529},
{"learn":[3.696182221],"iteration":615,"passed_time":0.2326054495,"remaining_time":0.1450007997},
{"learn":[3.694263278],"iteration":616,"passed_time":0.2328576444,"remaining_time":0.1445453449},
{"learn":[3.693810229],"iteration":617,"passed_time":0.2331185055,"remaining_time":0.1440959047},
{"learn":[3.690900932],"iteration":618,"passed_time":0.2333810749,"remaining_time":0.1436481252},
{"learn":[3.688020895],"iteration":619,"passed_time":0.2336171873,"remaining_time":0.1431847277},
{"learn":[3.685491894],"iteration":620,"passed_time":0.2338677573,"remaining_time":0.1427308857},
{"learn":[3.684328128],"iteration":621,"passed_time":0.2341256186,"remaining_time":0.1422821283},
{"learn":[3.680640153],"iteration":622,"passed_time":0.2344112284,"remaining_time":0.1418507754},
{"learn":[3.678932783],"iteration":623,"passed_time":0.2346852554,"remaining_time":0.1414129103},
{"learn":[3.674167041],"iteration":624,"passed_time":0.234962199,"remaining_time":0.1409773194},
{"learn":[3.672200976],"iteration":625,"passed_time":0.2352228935,"remaining_time":0.1405325274},
{"learn":[3.670606604],"iteration":626,"passed_time":0.2354722969,"remaining_time":0.1400816056},
{"learn":[3.665506042],"iteration":627,"passed_time":0.2357230335,"remaining_time":0.1396321154},
{"learn":[3.664214007],"iteration":628,"passed_time":0.2359705203,"remaining_time":0.1391813403},
{"learn":[3.66261643],"iteration":629,"passed_time":0.2362511304,"remaining_time":0.1387506639},
{"learn":[3.662118449],"iteration":630,"passed_time":0.2365394067,"remaining_time":0.1383249462},
{"learn":[3.660871366],"iteration":631,"passed_time":0.236935344,"remaining_time":0.1379623522},
{"learn":[3.656695243],"iteration":632,"passed_time":0.2371990799,"remaining_time":0.1375230053},
{"learn":[3.654497801],"iteration":633,"passed_time":0.237555311,"remaining_time":0.1371376085},
{"learn":[3.654189134],"iteration":634,"passed_time":0.2378084642,"remaining_time":0.1366930542},
{"learn":[3.653957699],"iteration":635,"passed_time":0.2380371603,"remaining_time":0.1362351043},
{"learn":[3.651920725],"iteration":636,"passed_time":0.2383063543,"remaining_time":0.1358009523},
{"learn":[3.65106705],"iteration":637,"passed_time":0.2386059217,"remaining_time":0.1353845512},
{"learn":[3.650612844],"iteration":638,"passed_time":0.2388800321,"remaining_time":0.1349541339},
{"learn":[3.649884732],"iteration":639,"passed_time":0.2391504761,"remaining_time":0.1345221428},
{"learn":[3.646276182],"iteration":640,"passed_time":0.2394381274,"remaining_time":0.1341002929},
{"learn":[3.645808194],"iteration":641,"passed_time":0.239808191,"remaining_time":0.1337248168},
{"learn":[3.645042989],"iteration":642,"passed_time":0.2400940925,"remaining_time":0.1333026299},
{"learn":[3.639864499],"iteration":643,"passed_time":0.2403452041,"remaining_time":0.1328616346},
{"learn":[3.637318478],"iteration":644,"passed_time":0.2405730253,"remaining_time":0.1324084093},
{"learn":[3.636344905],"iteration":645,"passed_time":0.2408765925,"remaining_time":0.1319973897},
{"learn":[3.634754643],"iteration":646,"passed_time":0.2411332455,"remaining_time":0.1315611061},
{"learn":[3.630724975],"iteration":647,"passed_time":0.2413933983,"remaining_time":0.1311272781},
{"learn":[3.629408252],"iteration":648,"passed_time":0.241643885,"remaining_time":0.1306887575},
{"learn":[3.62790646],"iteration":649,"passed_time":0.241888372,"remaining_time":0.1302475849},
{"learn":[3.627388973],"iteration":650,"passed_time":0.2422366867,"remaining_time":0.1298626785},
{"learn":[3.625163557],"iteration":651,"passed_time":0.2425370458,"remaining_time":0.1294522882},
{"learn":[3.623701985],"iteration":652,"passed_time":0.2427809494,"remaining_time":0.129012235},
{"learn":[3.622342639],"iteration":653,"passed_time":0.2430584763,"remaining_time":0.12859057},
{"learn":[3.621130639],"iteration":654,"passed_time":0.243315171,"remaining_time":0.1281583725},
{"learn":[3.619125665],"iteration":655,"passed_time":0.2435769904,"remaining_time":0.1277293974},
{"learn":[3.618878783],"iteration":656,"passed_time":0.2438152694,"remaining_time":0.1272886414},
{"learn":[3.616207429],"iteration":657,"passed_time":0.2440693808,"remaining_time":0.1268567299},
{"learn":[3.61206486],"iteration":658,"passed_time":0.2443519491,"remaining_time":0.1264400829},
{"learn":[3.611955873],"iteration":659,"passed_time":0.2445873533,"remaining_time":0.1259995456},
{"learn":[3.610713743],"iteration":660,"passed_time":0.2448769212,"remaining_time":0.1255874074},
{"learn":[3.610044025],"iteration":661,"passed_time":0.2451370323,"remaining_time":0.1251605996},
{"learn":[3.607342669],"iteration":662,"passed_time":0.2454192673,"remaining_time":0.1247455401},
{"learn":[3.602510618],"iteration":663,"passed_time":0.2456800034,"remaining_time":0.1243200017},
{"learn":[3.600492392],"iteration":664,"passed_time":0.2459351982,"remaining_time":0.1238921675},
{"learn":[3.597171065],"iteration":665,"passed_time":0.2461831016,"remaining_time":0.1234611951},
{"learn":[3.594358798],"iteration":666,"passed_time":0.2464379631,"remaining_time":0.1230342454},
{"learn":[3.593945251],"iteration":667,"passed_time":0.2467284893,"remaining_time":0.1226255366},
{"learn":[3.593607748],"iteration":668,"passed_time":0.2469942251,"remaining_time":0.1222049156},
{"learn":[3.592238714],"iteration":669,"passed_time":0.2473010005,"remaining_time":0.1218049704},
{"learn":[3.590144654],"iteration":670,"passed_time":0.2475848187,"remaining_time":0.1213940467},
{"learn":[3.587151536],"iteration":671,"passed_time":0.2478440965,"remaining_time":0.1209715233},
{"learn":[3.586070865],"iteration":672,"passed_time":0.2480915834,"remaining_time":0.120543756},
{"learn":[3.585102746],"iteration":673,"passed_time":0.2483348621,"remaining_time":0.1201144882},
{"learn":[3.584362847],"iteration":674,"passed_time":0.2485966398,"remaining_time":0.1196946784},
{"learn":[3.581407561],"iteration":675,"passed_time":0.2488342938,"remaining_time":0.119263774},
{"learn":[3.57919422],"iteration":676,"passed_time":0.2491348612,"remaining_time":0.1188634566},
{"learn":[3.577632204],"iteration":677,"passed_time":0.2494211792,"remaining_time":0.1184566662},
{"learn":[3.573911195],"iteration":678,"passed_time":0.2496845402,"remaining_time":0.1180393776},
{"learn":[3.573408216],"iteration":679,"passed_time":0.2499819411,"remaining_time":0.1176385605},
{"learn":[3.571076482],"iteration":680,"passed_time":0.2502470103,"remaining_time":0.117222902},
{"learn":[3.568177107],"iteration":681,"passed_time":0.2504719983,"remaining_time":0.1167889963},
{"learn":[3.564824621],"iteration":682,"passed_time":0.250733401,"remaining_time":0.1163726034},
{"learn":[3.562475026],"iteration":683,"passed_time":0.2509805546,"remaining_time":0.1159500808},
{"learn":[3.561226889],"iteration":684,"passed_time":0.2512443738,"remaining_time":0.115535734},
{"learn":[3.559383467],"iteration":685,"passed_time":0.2515104847,"remaining_time":0.1151228749},
{"learn":[3.555209766],"iteration":686,"passed_time":0.2517885115,"remaining_time":0.1147158721},
{"learn":[3.55345383],"iteration":687,"passed_time":0.252049081,"remaining_time":0.1143013274},
{"learn":[3.552300968],"iteration":688,"passed_time":0.2523818133,"remaining_time":0.1139198025},
{"learn":[3.551253986],"iteration":689,"passed_time":0.2527526269,"remaining_time":0.113555528},
{"learn":[3.549807725],"iteration":690,"passed_time":0.2530357368,"remaining_time":0.1131520154},
{"learn":[3.547992926],"iteration":691,"passed_time":0.253300431,"remaining_time":0.1127406543},
{"learn":[3.545438607],"iteration":692,"passed_time":0.253583166,"remaining_time":0.1123377085},
{"learn":[3.543313763],"iteration":693,"passed_time":0.2538816501,"remaining_time":0.1119420532},
{"learn":[3.542962896],"iteration":694,"passed_time":0.2541737179,"remaining_time":0.1115438618},
{"learn":[3.539800465],"iteration":695,"passed_time":0.2544478283,"remaining_time":0.1111381319},
{"learn":[3.53953187],"iteration":696,"passed_time":0.2547282717,"remaining_time":0.1107355327},
{"learn":[3.536332425],"iteration":697,"passed_time":0.2550352137,"remaining_time":0.1103447486},
{"learn":[3.534993327],"iteration":698,"passed_time":0.2552887419,"remaining_time":0.1099312036},
{"learn":[3.531637011],"iteration":699,"passed_time":0.255592684,"remaining_time":0.1095397217},
{"learn":[3.531040284],"iteration":700,"passed_time":0.2558504203,"remaining_time":0.1091287813},
{"learn":[3.529973872],"iteration":701,"passed_time":0.2560902408,"remaining_time":0.108710672},
{"learn":[3.527325183],"iteration":702,"passed_time":0.2563436024,"remaining_time":0.1082987908},
{"learn":[3.527200815],"iteration":703,"passed_time":0.2566021303,"remaining_time":0.107889532},
{"learn":[3.523459911],"iteration":704,"passed_time":0.2568412842,"remaining_time":0.1074725941},
{"learn":[3.522729934],"iteration":705,"passed_time":0.257101562,"remaining_time":0.1070649564},
{"learn":[3.522260582],"iteration":706,"passed_time":0.2574155453,"remaining_time":0.1066799926},
{"learn":[3.518641591],"iteration":707,"passed_time":0.2577455277,"remaining_time":0.1063018278},
{"learn":[3.516856405],"iteration":708,"passed_time":0.2580372205,"remaining_time":0.1059080835},
{"learn":[3.515083413],"iteration":709,"passed_time":0.2582870822,"remaining_time":0.1054975406},
{"learn":[3.514671214],"iteration":710,"passed_time":0.2585379855,"remaining_time":0.1050878732},
{"learn":[3.512617621],"iteration":711,"passed_time":0.2588236787,"remaining_time":0.104692724},
{"learn":[3.510747971],"iteration":712,"passed_time":0.259104497,"remaining_time":0.1042959196},
{"learn":[3.508149266],"iteration":713,"passed_time":0.259349984,"remaining_time":0.1038852877},
{"learn":[3.504557165],"iteration":714,"passed_time":0.2595942626,"remaining_time":0.1034746362},
{"learn":[3.501367208],"iteration":715,"passed_time":0.2598942467,"remaining_time":0.1030865448},
{"learn":[3.497593362],"iteration":716,"passed_time":0.260157316,"remaining_time":0.1026841289},
{"learn":[3.496291169],"iteration":717,"passed_time":0.2604737991,"remaining_time":0.1023030799},
{"learn":[3.49330374],"iteration":718,"passed_time":0.2607394933,"remaining_time":0.1019023611},
{"learn":[3.490044385],"iteration":719,"passed_time":0.2610075207,"remaining_time":0.1015029247},
{"learn":[3.488891789],"iteration":720,"passed_time":0.2612628405,"remaining_time":0.1010989355},
{"learn":[3.486869081],"iteration":721,"passed_time":0.2615376175,"remaining_time":0.10070285},
{"learn":[3.486303638],"iteration":722,"passed_time":0.26180377,"remaining_time":0.1003037957},
{"learn":[3.486035862],"iteration":723,"passed_time":0.2620356743,"remaining_time":0.09989205264},
{"learn":[3.482668951],"iteration":724,"passed_time":0.2624083628,"remaining_time":0.09953420658},
{"learn":[3.47820549],"iteration":725,"passed_time":0.2627038887,"remaining_time":0.09914719768},
{"learn":[3.474392283],"iteration":726,"passed_time":0.2629767492,"remaining_time":0.09875192921},
{"learn":[3.472268163],"iteration":727,"passed_time":0.2632146949,"remaining_time":0.09834395193},
{"learn":[3.471209164],"iteration":728,"passed_time":0.2634502657,"remaining_time":0.09793555829},
{"learn":[3.470049971],"iteration":729,"passed_time":0.2637487914,"remaining_time":0.09755092286},
{"learn":[3.469078654],"iteration":730,"passed_time":0.2640441507,"remaining_time":0.09716535779},
{"learn":[3.468643292],"iteration":731,"passed_time":0.2643309271,"remaining_time":0.09677689681},
{"learn":[3.468134848],"iteration":732,"passed_time":0.2646009127,"remaining_time":0.09638259714},
{"learn":[3.467820182],"iteration":733,"passed_time":0.2648471496,"remaining_time":0.0959800297},
{"learn":[3.465776156],"iteration":734,"passed_time":0.2650948864,"remaining_time":0.09557842845},
{"learn":[3.463037608],"iteration":735,"passed_time":0.2653338737,"remaining_time":0.09517410688},
{"learn":[3.45965637],"iteration":736,"passed_time":0.265615817,"remaining_time":0.09478556293},
{"learn":[3.457275091],"iteration":737,"passed_time":0.2658766365,"remaining_time":0.09438980862},
{"learn":[3.455522955],"iteration":738,"passed_time":0.2661211651,"remaining_time":0.0939886659},
{"learn":[3.451270508],"iteration":739,"passed_time":0.2663834012,"remaining_time":0.09359416798},
{"learn":[3.450978947],"iteration":740,"passed_time":0.2666387626,"remaining_time":0.09319762417},
{"learn":[3.450608492],"iteration":741,"passed_time":0.2668959572,"remaining_time":0.09280209833},
{"learn":[3.448122004],"iteration":742,"passed_time":0.2671676094,"remaining_time":0.09241194566},
{"learn":[3.445646714],"iteration":743,"passed_time":0.2674966336,"remaining_time":0.09204185241},
{"learn":[3.44411263],"iteration":744,"passed_time":0.2677807851,"remaining_time":0.09165651034},
{"learn":[3.443264164],"iteration":745,"passed_time":0.2680700197,"remaining_time":0.09127317025},
{"learn":[3.439521363],"iteration":746,"passed_time":0.2683321308,"remaining_time":0.09088089569},
{"learn":[3.436809225],"iteration":747,"passed_time":0.2686224903,"remaining_time":0.09049848604},
{"learn":[3.435509465],"iteration":748,"passed_time":0.2689845127,"remaining_time":0.09014033737},
{"learn":[3.434450277],"iteration":749,"passed_time":0.2692356243,"remaining_time":0.08974520811},
{"learn":[3.431786753],"iteration":750,"passed_time":0.2695150678,"remaining_time":0.08935985603},
{"learn":[3.430150302],"iteration":751,"passed_time":0.2697743873,"remaining_time":0.08896814901},
{"learn":[3.42696281],"iteration":752,"passed_time":0.2701049114,"remaining_time":0.08860015021},
{"learn":[3.426870334],"iteration":753,"passed_time":0.2703226081,"remaining_time":0.08819543979},
{"learn":[3.425200309],"iteration":754,"passed_time":0.2705700949,"remaining_time":0.08780089174},
{"learn":[3.423383783],"iteration":755,"passed_time":0.2708415388,"remaining_time":0.08741446491},
{"learn":[3.422752979],"iteration":756,"passed_time":0.2711029416,"remaining_time":0.08702511863},
{"learn":[3.420845924],"iteration":757,"passed_time":0.2713359708,"remaining_time":0.08662705138},
{"learn":[3.418917862],"iteration":758,"passed_time":0.2715744165,"remaining_time":0.08623113883},
{"learn":[3.417095735],"iteration":759,"passed_time":0.271821195,"remaining_time":0.08583827211},
{"learn":[3.414391848],"iteration":760,"passed_time":0.2720667653,"remaining_time":0.08544540985},
{"learn":[3.41426711],"iteration":761,"passed_time":0.2723393758,"remaining_time":0.08506137983},
{"learn":[3.411976013],"iteration":762,"passed_time":0.2726189025,"remaining_time":0.08467979017},
{"learn":[3.408614844],"iteration":763,"passed_time":0.2728803053,"remaining_time":0.08429286917},
{"learn":[3.407906721],"iteration":764,"passed_time":0.2731409164,"remaining_time":0.08390603315},
{"learn":[3.407494015],"iteration":765,"passed_time":0.2734209848,"remaining_time":0.08352547056},
{"learn":[3.406287128],"iteration":766,"passed_time":0.2737250936,"remaining_time":0.08315247304},
{"learn":[3.404600442],"iteration":767,"passed_time":0.2739643726,"remaining_time":0.08276007088},
{"learn":[3.404012662],"iteration":768,"passed_time":0.2743358528,"remaining_time":0.08240777893},
{"learn":[3.400398762],"iteration":769,"passed_time":0.2746022553,"remaining_time":0.08202405028},
{"learn":[3.399737714],"iteration":770,"passed_time":0.2748483255,"remaining_time":0.08163458695},
{"learn":[3.399185251],"iteration":771,"passed_time":0.2750936874,"remaining_time":0.08124528593},
{"learn":[3.397245411],"iteration":772,"passed_time":0.2753495072,"remaining_time":0.08085942836},
{"learn":[3.396229831],"iteration":773,"passed_time":0.2756072018,"remaining_time":0.08047445426},
{"learn":[3.394002836],"iteration":774,"passed_time":0.275878104,"remaining_time":0.0800936431},
{"learn":[3.389617243],"iteration":775,"passed_time":0.2761332571,"remaining_time":0.07970856906},
{"learn":[3.385426488],"iteration":776,"passed_time":0.2763744109,"remaining_time":0.07931981163},
{"learn":[3.385072258],"iteration":777,"passed_time":0.2766135649,"remaining_time":0.07893086298},
{"learn":[3.383842366],"iteration":778,"passed_time":0.2768785924,"remaining_time":0.07854963918},
{"learn":[3.380110746],"iteration":779,"passed_time":0.2771290791,"remaining_time":0.07816461205},
{"learn":[3.378595218],"iteration":780,"passed_time":0.2773670664,"remaining_time":0.07777642451},
{"learn":[3.377371219],"iteration":781,"passed_time":0.2775882213,"remaining_time":0.0773839287},
{"learn":[3.375814782],"iteration":782,"passed_time":0.2778854971,"remaining_time":0.07701296664},
{"learn":[3.374195887],"iteration":783,"passed_time":0.2781734401,"remaining_time":0.07663962127},
{"learn":[3.373704309],"iteration":784,"passed_time":0.2785195884,"remaining_time":0.07628243504},
{"learn":[3.372971757],"iteration":785,"passed_time":0.2788042399,"remaining_time":0.07590853351},
{"learn":[3.371565136],"iteration":786,"passed_time":0.279040019,"remaining_time":0.07552163158},
{"learn":[3.3700309],"iteration":787,"passed_time":0.2793003802,"remaining_time":0.07514172664},
{"learn":[3.368186663],"iteration":788,"passed_time":0.2796409037,"remaining_time":0.07478356233},
{"learn":[3.366710398],"iteration":789,"passed_time":0.2799014731,"remaining_time":0.07440418906},
{"learn":[3.364598042],"iteration":790,"passed_time":0.2801538764,"remaining_time":0.07402295849},
{"learn":[3.36348442],"iteration":791,"passed_time":0.280399155,"remaining_time":0.07364018212},
{"learn":[3.362001759],"iteration":792,"passed_time":0.2807768015,"remaining_time":0.07329230507},
{"learn":[3.361580401],"iteration":793,"passed_time":0.2810500787,"remaining_time":0.07291727482},
{"learn":[3.359543675],"iteration":794,"passed_time":0.2813038985,"remaining_time":0.07253748326},
{"learn":[3.35766119],"iteration":795,"passed_time":0.2816872531,"remaining_time":0.07219120556},
{"learn":[3.354592969],"iteration":796,"passed_time":0.2819752794,"remaining_time":0.07182055423},
{"learn":[3.350985986],"iteration":797,"passed_time":0.2822367655,"remaining_time":0.07144339176},
{"learn":[3.349589624],"iteration":798,"passed_time":0.282546374,"remaining_time":0.07107862475},
{"learn":[3.349110856],"iteration":799,"passed_time":0.2828503162,"remaining_time":0.07071257904},
{"learn":[3.345315441],"iteration":800,"passed_time":0.2830843454,"remaining_time":0.07032931926},
{"learn":[3.34397474],"iteration":801,"passed_time":0.2833306656,"remaining_time":0.06994946607},
{"learn":[3.343800902],"iteration":802,"passed_time":0.2835894851,"remaining_time":0.06957301192},
{"learn":[3.342329465],"iteration":803,"passed_time":0.2838724284,"remaining_time":0.0692027313},
{"learn":[3.34220347],"iteration":804,"passed_time":0.2841348311,"remaining_time":0.06882769201},
{"learn":[3.341279219],"iteration":805,"passed_time":0.2843770265,"remaining_time":0.06844806842},
{"learn":[3.337329521],"iteration":806,"passed_time":0.2847742971,"remaining_time":0.06810587278},
{"learn":[3.336708453],"iteration":807,"passed_time":0.2851361111,"remaining_time":0.06775511551},
{"learn":[3.333252703],"iteration":808,"passed_time":0.2854280539,"remaining_time":0.06738783473},
{"learn":[3.332186769],"iteration":809,"passed_time":0.2857912846,"remaining_time":0.06703746181},
{"learn":[3.330594851],"iteration":810,"passed_time":0.2860378964,"remaining_time":0.06665987969},
{"learn":[3.327867442],"iteration":811,"passed_time":0.2862994242,"remaining_time":0.06628607358},
{"learn":[3.327563111],"iteration":812,"passed_time":0.2865405364,"remaining_time":0.06590784785},
{"learn":[3.326308994],"iteration":813,"passed_time":0.2868337707,"remaining_time":0.06554186899},
{"learn":[3.326249879],"iteration":814,"passed_time":0.2871687946,"remaining_time":0.0651855546},
{"learn":[3.322336238],"iteration":815,"passed_time":0.2875087765,"remaining_time":0.06483041038},
{"learn":[3.320491154],"iteration":816,"passed_time":0.2877643045,"remaining_time":0.06445638645},
{"learn":[3.320434271],"iteration":817,"passed_time":0.288012208,"remaining_time":0.06408095581},
{"learn":[3.319609638],"iteration":818,"passed_time":0.2882799437,"remaining_time":0.06371021956},
{"learn":[3.316182682],"iteration":819,"passed_time":0.2885557207,"remaining_time":0.06334149967},
{"learn":[3.313126612],"iteration":820,"passed_time":0.2888189984,"remaining_time":0.06297028101},
{"learn":[3.311222803],"iteration":821,"passed_time":0.28907036,"remaining_time":0.06259674462},
{"learn":[3.309627335],"iteration":822,"passed_time":0.2893334293,"remaining_time":0.06222602308},
{"learn":[3.307974895],"iteration":823,"passed_time":0.2896309552,"remaining_time":0.06186292246},
{"learn":[3.307321505],"iteration":824,"passed_time":0.2899077321,"remaining_time":0.06149557953},
{"learn":[3.306759087],"iteration":825,"passed_time":0.2901543023,"remaining_time":0.06112209273},
{"learn":[3.30484037],"iteration":826,"passed_time":0.2903925396,"remaining_time":0.06074716971},
{"learn":[3.30201994],"iteration":827,"passed_time":0.2906447762,"remaining_time":0.06037548491},
{"learn":[3.299302297],"iteration":828,"passed_time":0.2909314692,"remaining_time":0.06001119571},
{"learn":[3.298132671],"iteration":829,"passed_time":0.2912242453,"remaining_time":0.0596483394},
{"learn":[3.296976183],"iteration":830,"passed_time":0.2920614924,"remaining_time":0.05939638053},
{"learn":[3.293144745],"iteration":831,"passed_time":0.2923443524,"remaining_time":0.05903107115},
{"learn":[3.290284404],"iteration":832,"passed_time":0.292613338,"remaining_time":0.05866317821},
{"learn":[3.288285745],"iteration":833,"passed_time":0.2929921512,"remaining_time":0.05831738261},
{"learn":[3.286662667],"iteration":834,"passed_time":0.2932927602,"remaining_time":0.05795605441},
{"learn":[3.285692682],"iteration":835,"passed_time":0.293522873,"remaining_time":0.05758104206},
{"learn":[3.284565611],"iteration":836,"passed_time":0.2937571521,"remaining_time":0.05720718734},
{"learn":[3.283897383],"iteration":837,"passed_time":0.2940180549,"remaining_time":0.05683881253},
{"learn":[3.280712855],"iteration":838,"passed_time":0.2942576672,"remaining_time":0.05646660836},
{"learn":[3.280468341],"iteration":839,"passed_time":0.2945219448,"remaining_time":0.05609941805},
{"learn":[3.277814895],"iteration":840,"passed_time":0.2947641402,"remaining_time":0.05572829761},
{"learn":[3.276316385],"iteration":841,"passed_time":0.2950212098,"remaining_time":0.05536027453},
{"learn":[3.27557063],"iteration":842,"passed_time":0.2952984868,"remaining_time":0.05499627808},
{"learn":[3.27499628],"iteration":843,"passed_time":0.2955595978,"remaining_time":0.05462949913},
{"learn":[3.273569958],"iteration":844,"passed_time":0.2958168342,"remaining_time":0.05426225952},
{"learn":[3.269665595],"iteration":845,"passed_time":0.2960842366,"remaining_time":0.05389713054},
{"learn":[3.267984685],"iteration":846,"passed_time":0.2963425562,"remaining_time":0.05353059161},
{"learn":[3.267702508],"iteration":847,"passed_time":0.2965983759,"remaining_time":0.05316385983},
{"learn":[3.266671924],"iteration":848,"passed_time":0.2969486489,"remaining_time":0.05281418844},
{"learn":[3.265359825],"iteration":849,"passed_time":0.2972093434,"remaining_time":0.05244870765},
{"learn":[3.2618983],"iteration":850,"passed_time":0.2975027861,"remaining_time":0.05208920696},
{"learn":[3.260456253],"iteration":851,"passed_time":0.2977470231,"remaining_time":0.05172131386},
{"learn":[3.258389147],"iteration":852,"passed_time":0.2980016345,"remaining_time":0.05135549856},
{"learn":[3.258108469],"iteration":853,"passed_time":0.2982549543,"remaining_time":0.05098972287},
{"learn":[3.256424936],"iteration":854,"passed_time":0.2985260649,"remaining_time":0.05062722738},
{"learn":[3.254817983],"iteration":855,"passed_time":0.2987875093,"remaining_time":0.05026331933},
{"learn":[3.253898449],"iteration":856,"passed_time":0.2990644113,"remaining_time":0.04990222965},
{"learn":[3.253023652],"iteration":857,"passed_time":0.2993466879,"remaining_time":0.04954222574},
{"learn":[3.252845542],"iteration":858,"passed_time":0.2996007994,"remaining_time":0.04917777964},
{"learn":[3.252316026],"iteration":859,"passed_time":0.2998734932,"remaining_time":0.04881661517},
{"learn":[3.24975301],"iteration":860,"passed_time":0.3001595196,"remaining_time":0.04845780863},
{"learn":[3.249151075],"iteration":861,"passed_time":0.3005954131,"remaining_time":0.04812316358},
{"learn":[3.246257135],"iteration":862,"passed_time":0.3009092714,"remaining_time":0.04776891098},
{"learn":[3.243826471],"iteration":863,"passed_time":0.301167216,"remaining_time":0.04740595066},
{"learn":[3.243190653],"iteration":864,"passed_time":0.3014029118,"remaining_time":0.04703976079},
{"learn":[3.24008797],"iteration":865,"passed_time":0.3018068069,"remaining_time":0.04669989853},
{"learn":[3.240036811],"iteration":866,"passed_time":0.3021229568,"remaining_time":0.0463464282},
{"learn":[3.238676314],"iteration":867,"passed_time":0.3023728184,"remaining_time":0.04598296317},
{"learn":[3.237848782],"iteration":868,"passed_time":0.3026255133,"remaining_time":0.0456201867},
{"learn":[3.236405498],"iteration":869,"passed_time":0.3029234975,"remaining_time":0.04526443066},
{"learn":[3.233378068],"iteration":870,"passed_time":0.3031936497,"remaining_time":0.04490468521},
{"learn":[3.233169169],"iteration":871,"passed_time":0.3034453863,"remaining_time":0.04454244203},
{"learn":[3.232434885],"iteration":872,"passed_time":0.3036916649,"remaining_time":0.04417965801},
{"learn":[3.229978115],"iteration":873,"passed_time":0.3040446878,"remaining_time":0.04383252936},
{"learn":[3.229648848],"iteration":874,"passed_time":0.3043522547,"remaining_time":0.04347889353},
{"learn":[3.227208761],"iteration":875,"passed_time":0.3046871536,"remaining_time":0.04312923178},
{"learn":[3.226258869],"iteration":876,"passed_time":0.3049556809,"remaining_time":0.04277029505},
{"learn":[3.225331995],"iteration":877,"passed_time":0.3052512069,"remaining_time":0.04241531576},
{"learn":[3.221968268],"iteration":878,"passed_time":0.3055024435,"remaining_time":0.04205437504},
{"learn":[3.221166317],"iteration":879,"passed_time":0.3057625546,"remaining_time":0.04169489382},
{"learn":[3.220047503],"iteration":880,"passed_time":0.3060142912,"remaining_time":0.04133450699},
{"learn":[3.21982781],"iteration":881,"passed_time":0.3062658195,"remaining_time":0.04097433867},
{"learn":[3.216693405],"iteration":882,"passed_time":0.3065510543,"remaining_time":0.04061888262},
{"learn":[3.214798761],"iteration":883,"passed_time":0.3067959163,"remaining_time":0.04025828766},
{"learn":[3.214395085],"iteration":884,"passed_time":0.3071130244,"remaining_time":0.03990734216},
{"learn":[3.213470696],"iteration":885,"passed_time":0.3074673389,"remaining_time":0.03956126031},
{"learn":[3.211595017],"iteration":886,"passed_time":0.3078031543,"remaining_time":0.0392128032},
{"learn":[3.210965255],"iteration":887,"passed_time":0.3080840977,"remaining_time":0.03885745377},
{"learn":[3.209413583],"iteration":888,"passed_time":0.3083467087,"remaining_time":0.03849998276},
{"learn":[3.208331683],"iteration":889,"passed_time":0.3085947372,"remaining_time":0.03814092257},
{"learn":[3.207110711],"iteration":890,"passed_time":0.3088705975,"remaining_time":0.03778551642},
{"learn":[3.204519413],"iteration":891,"passed_time":0.3091464995,"remaining_time":0.03743029366},
{"learn":[3.201421296],"iteration":892,"passed_time":0.3095587275,"remaining_time":0.03709158326},
{"learn":[3.200691259],"iteration":893,"passed_time":0.3098785022,"remaining_time":0.03674174634},
{"learn":[3.200485067],"iteration":894,"passed_time":0.3101633204,"remaining_time":0.03638787557},
{"learn":[3.197467568],"iteration":895,"passed_time":0.3104897196,"remaining_time":0.03603898532},
{"learn":[3.195838544],"iteration":896,"passed_time":0.3108138691,"remaining_time":0.03568988686},
{"learn":[3.195671746],"iteration":897,"passed_time":0.3110582727,"remaining_time":0.03533178599},
{"learn":[3.194213094],"iteration":898,"passed_time":0.3113158007,"remaining_time":0.03497541253},
{"learn":[3.192884691],"iteration":899,"passed_time":0.3116463664,"remaining_time":0.03462737404},
{"learn":[3.188364239],"iteration":900,"passed_time":0.3119422673,"remaining_time":0.03427556544},
{"learn":[3.185219478],"iteration":901,"passed_time":0.3122387515,"remaining_time":0.03392394418},
{"learn":[3.184120387],"iteration":902,"passed_time":0.3125204449,"remaining_time":0.0335708562},
{"learn":[3.183725321],"iteration":903,"passed_time":0.3127783478,"remaining_time":0.03321539977},
{"learn":[3.181264554],"iteration":904,"passed_time":0.3130680407,"remaining_time":0.03286349599},
{"learn":[3.180741589],"iteration":905,"passed_time":0.3133395263,"remaining_time":0.03250984047},
{"learn":[3.179782639],"iteration":906,"passed_time":0.3135938044,"remaining_time":0.03215460177},
{"learn":[3.176377564],"iteration":907,"passed_time":0.3138115011,"remaining_time":0.03179587897},
{"learn":[3.174078182],"iteration":908,"passed_time":0.3140956527,"remaining_time":0.03144411924},
{"learn":[3.171242379],"iteration":909,"passed_time":0.3143687215,"remaining_time":0.03109141201},
{"learn":[3.170421012],"iteration":910,"passed_time":0.3146311658,"remaining_time":0.03073784167},
{"learn":[3.170087224],"iteration":911,"passed_time":0.3148757778,"remaining_time":0.03038275049},
{"learn":[3.167303059],"iteration":912,"passed_time":0.3151620126,"remaining_time":0.03003186757},
{"learn":[3.16705966],"iteration":913,"passed_time":0.3154031247,"remaining_time":0.02967688044},
{"learn":[3.165667683],"iteration":914,"passed_time":0.3156511115,"remaining_time":0.02932278085},
{"learn":[3.164689733],"iteration":915,"passed_time":0.3159826355,"remaining_time":0.02897657356},
{"learn":[3.163311455],"iteration":916,"passed_time":0.3162725784,"remaining_time":0.02862663469},
{"learn":[3.159425016],"iteration":917,"passed_time":0.316531523,"remaining_time":0.02827405761},
{"learn":[3.159327058],"iteration":918,"passed_time":0.3167871344,"remaining_time":0.02792139052},
{"learn":[3.15819426],"iteration":919,"passed_time":0.3171054508,"remaining_time":0.02757438702},
{"learn":[3.157086603],"iteration":920,"passed_time":0.3174154759,"remaining_time":0.02722673463},
{"learn":[3.153354154],"iteration":921,"passed_time":0.3176574214,"remaining_time":0.02687340441},
{"learn":[3.153261317],"iteration":922,"passed_time":0.3179207823,"remaining_time":0.0265221021},
{"learn":[3.153168454],"iteration":923,"passed_time":0.3181621028,"remaining_time":0.02616917729},
{"learn":[3.152080399],"iteration":924,"passed_time":0.3184098813,"remaining_time":0.0258170174},
{"learn":[3.151635144],"iteration":925,"passed_time":0.3187045323,"remaining_time":0.02546882871},
{"learn":[3.147762655],"iteration":926,"passed_time":0.3189934752,"remaining_time":0.02512030603},
{"learn":[3.147172317],"iteration":927,"passed_time":0.3192452952,"remaining_time":0.02476903152},
{"learn":[3.146254125],"iteration":928,"passed_time":0.3195524038,"remaining_time":0.02442219663},
{"learn":[3.144869828],"iteration":929,"passed_time":0.3198460965,"remaining_time":0.02407443737},
{"learn":[3.143466218],"iteration":930,"passed_time":0.3200963332,"remaining_time":0.02372357357},
{"learn":[3.141919643],"iteration":931,"passed_time":0.320387901,"remaining_time":0.02337594127},
{"learn":[3.141054135],"iteration":932,"passed_time":0.3206398459,"remaining_time":0.02302558379},
{"learn":[3.139390417],"iteration":933,"passed_time":0.320888291,"remaining_time":0.02267518973},
{"learn":[3.139025283],"iteration":934,"passed_time":0.3211299032,"remaining_time":0.02232453872},
{"learn":[3.137824183],"iteration":935,"passed_time":0.3214927588,"remaining_time":0.02198241086},
{"learn":[3.135620453],"iteration":936,"passed_time":0.3218545312,"remaining_time":0.02164016592},
{"learn":[3.13443178],"iteration":937,"passed_time":0.3221098093,"remaining_time":0.02129084028},
{"learn":[3.132765713],"iteration":938,"passed_time":0.3223807949,"remaining_time":0.02094273534},
{"learn":[3.131434124],"iteration":939,"passed_time":0.3226726544,"remaining_time":0.02059612687},
{"learn":[3.128384262],"iteration":940,"passed_time":0.3229613473,"remaining_time":0.02024943623},
{"learn":[3.128120455],"iteration":941,"passed_time":0.3232216668,"remaining_time":0.01990112173},
{"learn":[3.126314615],"iteration":942,"passed_time":0.3234793197,"remaining_time":0.01955283269},
{"learn":[3.125409666],"iteration":943,"passed_time":0.323712224,"remaining_time":0.01920326753},
{"learn":[3.123072589],"iteration":944,"passed_time":0.323968252,"remaining_time":0.01885529509},
{"learn":[3.122921099],"iteration":945,"passed_time":0.3242114474,"remaining_time":0.01850678453},
{"learn":[3.122182662],"iteration":946,"passed_time":0.3245214726,"remaining_time":0.01816223659},
{"learn":[3.120040951],"iteration":947,"passed_time":0.324770876,"remaining_time":0.01781443624},
{"learn":[3.118767799],"iteration":948,"passed_time":0.3250541942,"remaining_time":0.01746866587},
{"learn":[3.118203218],"iteration":949,"passed_time":0.325333471,"remaining_time":0.01712281426},
{"learn":[3.116343362],"iteration":950,"passed_time":0.3257228253,"remaining_time":0.01678277438},
{"learn":[3.11480829],"iteration":951,"passed_time":0.3260089767,"remaining_time":0.0164374274},
{"learn":[3.112607903],"iteration":952,"passed_time":0.3263632495,"remaining_time":0.01609556425},
{"learn":[3.111661241],"iteration":953,"passed_time":0.3266377349,"remaining_time":0.01574982789},
{"learn":[3.110249676],"iteration":954,"passed_time":0.3268988044,"remaining_time":0.01540360858},
{"learn":[3.107333579],"iteration":955,"passed_time":0.3271761646,"remaining_time":0.0150583172},
{"learn":[3.107149851],"iteration":956,"passed_time":0.3274346508,"remaining_time":0.01471231973},
{"learn":[3.106867336],"iteration":957,"passed_time":0.3276958869,"remaining_time":0.01436662552},
{"learn":[3.10364681],"iteration":958,"passed_time":0.3279616644,"remaining_time":0.01402130161},
{"learn":[3.102703811],"iteration":959,"passed_time":0.3282418162,"remaining_time":0.01367674234},
{"learn":[3.101469264],"iteration":960,"passed_time":0.3285335923,"remaining_time":0.01333278887},
{"learn":[3.09863569],"iteration":961,"passed_time":0.3288056195,"remaining_time":0.01298816376},
{"learn":[3.09645939],"iteration":962,"passed_time":0.3291148947,"remaining_time":0.01264512057},
{"learn":[3.096240186],"iteration":963,"passed_time":0.3293710477,"remaining_time":0.01230016361},
{"learn":[3.094838828],"iteration":964,"passed_time":0.3296711151,"remaining_time":0.01195698345},
{"learn":[3.094176802],"iteration":965,"passed_time":0.3300024725,"remaining_time":0.01161499385},
{"learn":[3.093182279],"iteration":966,"passed_time":0.330274458,"remaining_time":0.01127100012},
{"learn":[3.090150687],"iteration":967,"passed_time":0.3305222365,"remaining_time":0.01092635492},
{"learn":[3.088612829],"iteration":968,"passed_time":0.3307975968,"remaining_time":0.01058279205},
{"learn":[3.087153684],"iteration":969,"passed_time":0.3310769153,"remaining_time":0.01023949222},
{"learn":[3.085866843],"iteration":970,"passed_time":0.3313445677,"remaining_time":0.009895975759},
{"learn":[3.082669094],"iteration":971,"passed_time":0.3317082983,"remaining_time":0.009555383079},
{"learn":[3.081047548],"iteration":972,"passed_time":0.3319670345,"remaining_time":0.009211829324},
{"learn":[3.079684322],"iteration":973,"passed_time":0.3322207294,"remaining_time":0.008868315157},
{"learn":[3.07613431],"iteration":974,"passed_time":0.3324825071,"remaining_time":0.008525192489},
{"learn":[3.074005935],"iteration":975,"passed_time":0.3327336187,"remaining_time":0.008181974231},
{"learn":[3.072988853],"iteration":976,"passed_time":0.3330100207,"remaining_time":0.007839539893},
{"learn":[3.072344268],"iteration":977,"passed_time":0.3332902974,"remaining_time":0.007497327754},
{"learn":[3.070654438],"iteration":978,"passed_time":0.3335974477,"remaining_time":0.007155818593},
{"learn":[3.069724506],"iteration":979,"passed_time":0.3339819689,"remaining_time":0.006815958549},
{"learn":[3.067763166],"iteration":980,"passed_time":0.3342502463,"remaining_time":0.006473756045},
{"learn":[3.066737893],"iteration":981,"passed_time":0.3345550634,"remaining_time":0.006132373871},
{"learn":[3.065248174],"iteration":982,"passed_time":0.3348597972,"remaining_time":0.005791064651},
{"learn":[3.063186837],"iteration":983,"passed_time":0.3351641976,"remaining_time":0.005449824352},
{"learn":[3.062880371],"iteration":984,"passed_time":0.335426517,"remaining_time":0.005108018026},
{"learn":[3.061288645],"iteration":985,"passed_time":0.3357302092,"remaining_time":0.004766960374},
{"learn":[3.059970575],"iteration":986,"passed_time":0.3360041946,"remaining_time":0.004425587163},
{"learn":[3.059576341],"iteration":987,"passed_time":0.33624714,"remaining_time":0.00408397336},
{"learn":[3.058175919],"iteration":988,"passed_time":0.3365619566,"remaining_time":0.003743358465},
{"learn":[3.056830702],"iteration":989,"passed_time":0.3368574825,"remaining_time":0.003402600833},
{"learn":[3.056336579],"iteration":990,"passed_time":0.3371229684,"remaining_time":0.00306166167},
{"learn":[3.055810414],"iteration":991,"passed_time":0.3373763299,"remaining_time":0.002720776854},
{"learn":[3.055476518],"iteration":992,"passed_time":0.3376560233,"remaining_time":0.002380253941},
{"learn":[3.053331734],"iteration":993,"passed_time":0.337931092,"remaining_time":0.002039825505},
{"learn":[3.050890374],"iteration":994,"passed_time":0.3382030775,"remaining_time":0.001699512952},
{"learn":[3.04972623],"iteration":995,"passed_time":0.3384977285,"remaining_time":0.001359428629},
{"learn":[3.047217327],"iteration":996,"passed_time":0.3387424655,"remaining_time":0.001019285252},
{"learn":[3.047155483],"iteration":997,"passed_time":0.3389804528,"remaining_time":0.0006793195447},
{"learn":[3.04430671],"iteration":998,"passed_time":0.3392326477,"remaining_time":0.0003395722199},
{"learn":[3.042664195],"iteration":999,"passed_time":0.3395576721,"remaining_time":0}
]}